Display_module/Display_module.v
module Display_module (
    // Clock and reset
    input wire clk,              // System clock
    input wire reset,            // Synchronous reset, active high
    
    // Status inputs
    input wire [5:0] vehicle_count,     // Current number of vehicles in parking
    input wire [5:0] available_spaces,  // Number of available parking spaces
    input wire [2:0] current_state,     // Current state of FSM
    input wire [1:0] barrier_status,    // Status of entry/exit barriers
    input wire alarm,                   // Alarm signal
    input wire [7:0] fee_amount,        // Parking fee amount
    
    // Display outputs
    output reg [7:0] segment_display,   // 7-segment display control signal
    output reg [3:0] digit_select,      // Digit selection for display
    output reg [3:0] led_indicators     // System status LED indicators
);

    // Parameters for display refresh
    parameter REFRESH_RATE = 1000;  // Display refresh rate in clock cycles
    
    // Internal registers
    reg [9:0] refresh_counter;      // Counter for display refresh
    reg [1:0] digit_index;          // Current digit to display
    reg [3:0] current_digit;        // Value of current digit
    
    // 7-segment display patterns for digits 0-9
    function [7:0] get_segment_pattern;
        input [3:0] digit;
        begin
            case (digit)
                4'h0: get_segment_pattern = 8'b11000000;  // 0
                4'h1: get_segment_pattern = 8'b11111001;  // 1
                4'h2: get_segment_pattern = 8'b10100100;  // 2
                4'h3: get_segment_pattern = 8'b10110000;  // 3
                4'h4: get_segment_pattern = 8'b10011001;  // 4
                4'h5: get_segment_pattern = 8'b10010010;  // 5
                4'h6: get_segment_pattern = 8'b10000010;  // 6
                4'h7: get_segment_pattern = 8'b11111000;  // 7
                4'h8: get_segment_pattern = 8'b10000000;  // 8
                4'h9: get_segment_pattern = 8'b10010000;  // 9
                default: get_segment_pattern = 8'b11111111; // All segments off
            endcase
        end
    endfunction
    
    // Display refresh logic
    always @(posedge clk) begin
        if (reset) begin
            refresh_counter <= 10'd0;
            digit_index <= 2'd0;
            segment_display <= 8'b11111111; // All segments off
            digit_select <= 4'b1111;        // All digits off
            current_digit <= 4'd0;
        end else begin
            // Update refresh counter
            if (refresh_counter < REFRESH_RATE) begin
                refresh_counter <= refresh_counter + 1'b1;
            end else begin
                refresh_counter <= 10'd0;
                
                // Rotate through digits
                digit_index <= digit_index + 1'b1;
                
                // Select current digit
                case (digit_index)
                    2'b00: begin
                        digit_select <= 4'b1110; // Enable digit 0 (rightmost)
                        current_digit <= available_spaces[3:0]; // Display lower 4 bits
                    end
                    2'b01: begin
                        digit_select <= 4'b1101; // Enable digit 1
                        current_digit <= {2'b00, available_spaces[5:4]}; // Display upper 2 bits
                    end
                    2'b10: begin
                        digit_select <= 4'b1011; // Enable digit 2
                        current_digit <= vehicle_count[3:0]; // Display lower 4 bits
                    end
                    2'b11: begin
                        digit_select <= 4'b0111; // Enable digit 3 (leftmost)
                        current_digit <= {2'b00, vehicle_count[5:4]}; // Display upper 2 bits
                    end
                endcase
                
                // Set segment pattern for current digit
                segment_display <= get_segment_pattern(current_digit);
            end
        end
    end
    
    // LED indicators logic
    always @(posedge clk) begin
        if (reset) begin
            led_indicators <= 4'b0000;
        end else begin
            // LED 0: Parking availability status
            led_indicators[0] <= (available_spaces > 0) ? 1'b1 : 1'b0;
            
            // LED 1: Barrier status
            led_indicators[1] <= (barrier_status != 2'b00) ? 1'b1 : 1'b0;
            
            // LED 2: System state indicator (blinks in emergency)
            led_indicators[2] <= (current_state == 3'b111) ? refresh_counter[9] : 1'b0;
            
            // LED 3: Alarm indicator
            led_indicators[3] <= alarm;
        end
    end

endmodule

Display_module/Display_module_tb.v
module Display_module_tb;
    // Parameters
    parameter CLK_PERIOD = 10;       // Clock period in ns
    parameter REFRESH_RATE = 100;    // Shorter refresh rate for simulation
    
    // Testbench signals
    reg clk;
    reg reset;
    reg [5:0] vehicle_count;
    reg [5:0] available_spaces;
    reg [2:0] current_state;
    reg [1:0] barrier_status;
    reg alarm;
    reg [7:0] fee_amount;
    
    wire [7:0] segment_display;
    wire [3:0] digit_select;
    wire [3:0] led_indicators;
    
    // State names for display
    reg [64*8-1:0] state_name;
    
    // Instantiate the Unit Under Test (UUT)
    Display_module #(
        .REFRESH_RATE(REFRESH_RATE)
    ) uut (
        .clk(clk),
        .reset(reset),
        .vehicle_count(vehicle_count),
        .available_spaces(available_spaces),
        .current_state(current_state),
        .barrier_status(barrier_status),
        .alarm(alarm),
        .fee_amount(fee_amount),
        .segment_display(segment_display),
        .digit_select(digit_select),
        .led_indicators(led_indicators)
    );
    
    // VCD file generation for GTKWave
    initial begin
        $dumpfile("display_module_waveform.vcd");
        $dumpvars(0, Display_module_tb);
    end
    
    // Clock generation
    initial begin
        clk = 0;
        forever #(CLK_PERIOD/2) clk = ~clk;
    end
    
    // Function to convert state to string for display
    always @(*) begin
        case(current_state)
            3'b000: state_name = "IDLE";
            3'b001: state_name = "VEHICLE_DETECTED";
            3'b010: state_name = "CARD_VERIFICATION";
            3'b011: state_name = "OPEN_BARRIER";
            3'b100: state_name = "VEHICLE_PASSING";
            3'b101: state_name = "CLOSE_BARRIER";
            3'b110: state_name = "UPDATE_COUNT";
            3'b111: state_name = "EMERGENCY_MODE";
            default: state_name = "UNKNOWN";
        endcase
    end
    
    // Function to convert barrier status to string
    function [64*8-1:0] barrier_status_to_string;
        input [1:0] status;
        begin
            case(status)
                2'b00: barrier_status_to_string = "BARRIERS_CLOSED";
                2'b01: barrier_status_to_string = "ENTRY_OPEN";
                2'b10: barrier_status_to_string = "EXIT_OPEN";
                2'b11: barrier_status_to_string = "BOTH_OPEN";
                default: barrier_status_to_string = "UNKNOWN";
            endcase
        end
    endfunction
    
    // Function to decode 7-segment display
    function [3:0] decode_7segment;
        input [7:0] segment;
        begin
            case(segment)
                8'b11000000: decode_7segment = 4'd0;
                8'b11111001: decode_7segment = 4'd1;
                8'b10100100: decode_7segment = 4'd2;
                8'b10110000: decode_7segment = 4'd3;
                8'b10011001: decode_7segment = 4'd4;
                8'b10010010: decode_7segment = 4'd5;
                8'b10000010: decode_7segment = 4'd6;
                8'b11111000: decode_7segment = 4'd7;
                8'b10000000: decode_7segment = 4'd8;
                8'b10010000: decode_7segment = 4'd9;
                default: decode_7segment = 4'd15; // Invalid
            endcase
        end
    endfunction
    
    // Display selected digit and LED status
    always @(digit_select or segment_display or led_indicators) begin
        $display("Time=%0t: Digit Select=%b, Segment Display=%b (Value=%0d), LEDs=%b", 
                 $time, digit_select, segment_display, decode_7segment(segment_display), led_indicators);
    end
    
    // Test stimulus
    initial begin
        // Initialize inputs
        reset = 1;
        vehicle_count = 6'd0;
        available_spaces = 6'd63;
        current_state = 3'b000; // IDLE
        barrier_status = 2'b00; // BARRIERS_CLOSED
        alarm = 0;
        fee_amount = 8'd0;
        
        // Apply reset
        #(CLK_PERIOD*2);
        reset = 0;
        #(CLK_PERIOD*10);
        
        // Display initial state
        $display("\nTime=%0t: Initial state - vehicle_count=%0d, available_spaces=%0d, state=%s, barrier_status=%s", 
                 $time, vehicle_count, available_spaces, state_name, barrier_status_to_string(barrier_status));
        
        // Test Case 1: Normal parking operation
        $display("\nTest Case 1: Normal parking operation");
        vehicle_count = 6'd5;
        available_spaces = 6'd58;
        current_state = 3'b000; // IDLE
        #(CLK_PERIOD*REFRESH_RATE*10); // Wait for display refresh cycles
        
        // Test Case 2: Vehicle detected
        $display("\nTest Case 2: Vehicle detected");
        current_state = 3'b001; // VEHICLE_DETECTED
        #(CLK_PERIOD*REFRESH_RATE*5);
        
        // Test Case 3: Card verification
        $display("\nTest Case 3: Card verification");
        current_state = 3'b010; // CARD_VERIFICATION
        #(CLK_PERIOD*REFRESH_RATE*5);
        
        // Test Case 4: Open barrier
        $display("\nTest Case 4: Open barrier");
        current_state = 3'b011; // OPEN_BARRIER
        barrier_status = 2'b01; // ENTRY_OPEN
        #(CLK_PERIOD*REFRESH_RATE*5);
        
        // Test Case 5: Vehicle passing
        $display("\nTest Case 5: Vehicle passing");
        current_state = 3'b100; // VEHICLE_PASSING
        #(CLK_PERIOD*REFRESH_RATE*5);
        
        // Test Case 6: Close barrier
        $display("\nTest Case 6: Close barrier");
        current_state = 3'b101; // CLOSE_BARRIER
        barrier_status = 2'b00; // BARRIERS_CLOSED
        #(CLK_PERIOD*REFRESH_RATE*5);
        
        // Test Case 7: Update count
        $display("\nTest Case 7: Update count");
        current_state = 3'b110; // UPDATE_COUNT
        vehicle_count = 6'd6;
        available_spaces = 6'd57;
        #(CLK_PERIOD*REFRESH_RATE*5);
        
        // Test Case 8: Low space warning
        $display("\nTest Case 8: Low space warning");
        vehicle_count = 6'd60;
        available_spaces = 6'd3;
        current_state = 3'b000; // IDLE
        #(CLK_PERIOD*REFRESH_RATE*5);
        
        // Test Case 9: Parking full
        $display("\nTest Case 9: Parking full");
        vehicle_count = 6'd63;
        available_spaces = 6'd0;
        #(CLK_PERIOD*REFRESH_RATE*5);
        
        // Test Case 10: Fee calculation
        $display("\nTest Case 10: Fee calculation");
        fee_amount = 8'd75; // $75 fee
        #(CLK_PERIOD*REFRESH_RATE*5);
        
        // Test Case 11: Alarm triggered
        $display("\nTest Case 11: Alarm triggered");
        alarm = 1;
        #(CLK_PERIOD*REFRESH_RATE*5);
        
        // Test Case 12: Emergency mode
        $display("\nTest Case 12: Emergency mode");
        current_state = 3'b111; // EMERGENCY_MODE
        barrier_status = 2'b11; // BOTH_OPEN
        #(CLK_PERIOD*REFRESH_RATE*10); // Wait longer to see LED blinking
        
        // Test Case 13: Exit operation
        $display("\nTest Case 13: Exit operation");
        alarm = 0;
        current_state = 3'b001; // VEHICLE_DETECTED
        barrier_status = 2'b00; // BARRIERS_CLOSED
        #(CLK_PERIOD*REFRESH_RATE*2);
        
        current_state = 3'b011; // OPEN_BARRIER
        barrier_status = 2'b10; // EXIT_OPEN
        #(CLK_PERIOD*REFRESH_RATE*2);
        
        current_state = 3'b100; // VEHICLE_PASSING
        #(CLK_PERIOD*REFRESH_RATE*2);
        
        current_state = 3'b101; // CLOSE_BARRIER
        barrier_status = 2'b00; // BARRIERS_CLOSED
        #(CLK_PERIOD*REFRESH_RATE*2);
        
        current_state = 3'b110; // UPDATE_COUNT
        vehicle_count = 6'd62;
        available_spaces = 6'd1;
        #(CLK_PERIOD*REFRESH_RATE*2);
        
        current_state = 3'b000; // IDLE
        #(CLK_PERIOD*REFRESH_RATE*5);
        
        // Test Case 14: Reset during operation
        $display("\nTest Case 14: Reset during operation");
        reset = 1;
        #(CLK_PERIOD*2);
        reset = 0;
        vehicle_count = 6'd0;
        available_spaces = 6'd63;
        current_state = 3'b000; // IDLE
        barrier_status = 2'b00; // BARRIERS_CLOSED
        alarm = 0;
        fee_amount = 8'd0;
        #(CLK_PERIOD*REFRESH_RATE*5);
        
        // End simulation
        $display("\nSimulation completed successfully");
        $finish;
    end
endmodule

Display_module/display_module_waveform.vcd
$date
	Mon Jun 16 12:27:22 2025
$end
$version
	Icarus Verilog
$end
$timescale
	1s
$end
$scope module Display_module_tb $end
$var wire 8 ! segment_display [7:0] $end
$var wire 4 " led_indicators [3:0] $end
$var wire 4 # digit_select [3:0] $end
$var parameter 32 $ CLK_PERIOD $end
$var parameter 32 % REFRESH_RATE $end
$var reg 1 & alarm $end
$var reg 6 ' available_spaces [5:0] $end
$var reg 2 ( barrier_status [1:0] $end
$var reg 1 ) clk $end
$var reg 3 * current_state [2:0] $end
$var reg 8 + fee_amount [7:0] $end
$var reg 1 , reset $end
$var reg 512 - state_name [511:0] $end
$var reg 6 . vehicle_count [5:0] $end
$scope function barrier_status_to_string $end
$var reg 2 / status [1:0] $end
$upscope $end
$scope function decode_7segment $end
$var reg 8 0 segment [7:0] $end
$upscope $end
$scope module uut $end
$var wire 1 & alarm $end
$var wire 6 1 available_spaces [5:0] $end
$var wire 2 2 barrier_status [1:0] $end
$var wire 1 ) clk $end
$var wire 3 3 current_state [2:0] $end
$var wire 8 4 fee_amount [7:0] $end
$var wire 1 , reset $end
$var wire 6 5 vehicle_count [5:0] $end
$var parameter 32 6 REFRESH_RATE $end
$var reg 4 7 current_digit [3:0] $end
$var reg 2 8 digit_index [1:0] $end
$var reg 4 9 digit_select [3:0] $end
$var reg 4 : led_indicators [3:0] $end
$var reg 10 ; refresh_counter [9:0] $end
$var reg 8 < segment_display [7:0] $end
$scope function get_segment_pattern $end
$var reg 4 = digit [3:0] $end
$upscope $end
$upscope $end
$upscope $end
$enddefinitions $end
$comment Show the parameter values. $end
$dumpall
b1100100 6
b1100100 %
b1010 $
$end
#0
$dumpvars
bx =
bx <
bx ;
bx :
bx 9
bx 8
bx 7
b0 5
b0 4
b0 3
b0 2
b111111 1
bx 0
bx /
b0 .
b1001001010001000100110001000101 -
1,
b0 +
b0 *
0)
b0 (
b111111 '
0&
bx #
bx "
bx !
$end
#5
b11111111 0
b0 7
b1111 #
b1111 9
b11111111 !
b11111111 <
b0 8
b0 ;
b0 "
b0 :
1)
#10
0)
#15
1)
#20
0)
0,
#25
b1 ;
b1 "
b1 :
1)
#30
0)
#35
b10 ;
1)
#40
0)
#45
b11 ;
1)
#50
0)
#55
b100 ;
1)
#60
0)
#65
b101 ;
1)
#70
0)
#75
b110 ;
1)
#80
0)
#85
b111 ;
1)
#90
0)
#95
b1000 ;
1)
#100
0)
#105
b1001 ;
1)
#110
0)
#115
b1010 ;
1)
#120
0)
b111010 '
b111010 1
b101 .
b101 5
b0 /
#125
b1011 ;
1)
#130
0)
#135
b1100 ;
1)
#140
0)
#145
b1101 ;
1)
#150
0)
#155
b1110 ;
1)
#160
0)
#165
b1111 ;
1)
#170
0)
#175
b10000 ;
1)
#180
0)
#185
b10001 ;
1)
#190
0)
#195
b10010 ;
1)
#200
0)
#205
b10011 ;
1)
#210
0)
#215
b10100 ;
1)
#220
0)
#225
b10101 ;
1)
#230
0)
#235
b10110 ;
1)
#240
0)
#245
b10111 ;
1)
#250
0)
#255
b11000 ;
1)
#260
0)
#265
b11001 ;
1)
#270
0)
#275
b11010 ;
1)
#280
0)
#285
b11011 ;
1)
#290
0)
#295
b11100 ;
1)
#300
0)
#305
b11101 ;
1)
#310
0)
#315
b11110 ;
1)
#320
0)
#325
b11111 ;
1)
#330
0)
#335
b100000 ;
1)
#340
0)
#345
b100001 ;
1)
#350
0)
#355
b100010 ;
1)
#360
0)
#365
b100011 ;
1)
#370
0)
#375
b100100 ;
1)
#380
0)
#385
b100101 ;
1)
#390
0)
#395
b100110 ;
1)
#400
0)
#405
b100111 ;
1)
#410
0)
#415
b101000 ;
1)
#420
0)
#425
b101001 ;
1)
#430
0)
#435
b101010 ;
1)
#440
0)
#445
b101011 ;
1)
#450
0)
#455
b101100 ;
1)
#460
0)
#465
b101101 ;
1)
#470
0)
#475
b101110 ;
1)
#480
0)
#485
b101111 ;
1)
#490
0)
#495
b110000 ;
1)
#500
0)
#505
b110001 ;
1)
#510
0)
#515
b110010 ;
1)
#520
0)
#525
b110011 ;
1)
#530
0)
#535
b110100 ;
1)
#540
0)
#545
b110101 ;
1)
#550
0)
#555
b110110 ;
1)
#560
0)
#565
b110111 ;
1)
#570
0)
#575
b111000 ;
1)
#580
0)
#585
b111001 ;
1)
#590
0)
#595
b111010 ;
1)
#600
0)
#605
b111011 ;
1)
#610
0)
#615
b111100 ;
1)
#620
0)
#625
b111101 ;
1)
#630
0)
#635
b111110 ;
1)
#640
0)
#645
b111111 ;
1)
#650
0)
#655
b1000000 ;
1)
#660
0)
#665
b1000001 ;
1)
#670
0)
#675
b1000010 ;
1)
#680
0)
#685
b1000011 ;
1)
#690
0)
#695
b1000100 ;
1)
#700
0)
#705
b1000101 ;
1)
#710
0)
#715
b1000110 ;
1)
#720
0)
#725
b1000111 ;
1)
#730
0)
#735
b1001000 ;
1)
#740
0)
#745
b1001001 ;
1)
#750
0)
#755
b1001010 ;
1)
#760
0)
#765
b1001011 ;
1)
#770
0)
#775
b1001100 ;
1)
#780
0)
#785
b1001101 ;
1)
#790
0)
#795
b1001110 ;
1)
#800
0)
#805
b1001111 ;
1)
#810
0)
#815
b1010000 ;
1)
#820
0)
#825
b1010001 ;
1)
#830
0)
#835
b1010010 ;
1)
#840
0)
#845
b1010011 ;
1)
#850
0)
#855
b1010100 ;
1)
#860
0)
#865
b1010101 ;
1)
#870
0)
#875
b1010110 ;
1)
#880
0)
#885
b1010111 ;
1)
#890
0)
#895
b1011000 ;
1)
#900
0)
#905
b1011001 ;
1)
#910
0)
#915
b1011010 ;
1)
#920
0)
#925
b1011011 ;
1)
#930
0)
#935
b1011100 ;
1)
#940
0)
#945
b1011101 ;
1)
#950
0)
#955
b1011110 ;
1)
#960
0)
#965
b1011111 ;
1)
#970
0)
#975
b1100000 ;
1)
#980
0)
#985
b1100001 ;
1)
#990
0)
#995
b1100010 ;
1)
#1000
0)
#1005
b1100011 ;
1)
#1010
0)
#1015
b1100100 ;
1)
#1020
0)
#1025
b11000000 0
b11000000 !
b11000000 <
b1010 7
b1110 #
b1110 9
b1 8
b0 ;
b0 =
1)
#1030
0)
#1035
b1 ;
1)
#1040
0)
#1045
b10 ;
1)
#1050
0)
#1055
b11 ;
1)
#1060
0)
#1065
b100 ;
1)
#1070
0)
#1075
b101 ;
1)
#1080
0)
#1085
b110 ;
1)
#1090
0)
#1095
b111 ;
1)
#1100
0)
#1105
b1000 ;
1)
#1110
0)
#1115
b1001 ;
1)
#1120
0)
#1125
b1010 ;
1)
#1130
0)
#1135
b1011 ;
1)
#1140
0)
#1145
b1100 ;
1)
#1150
0)
#1155
b1101 ;
1)
#1160
0)
#1165
b1110 ;
1)
#1170
0)
#1175
b1111 ;
1)
#1180
0)
#1185
b10000 ;
1)
#1190
0)
#1195
b10001 ;
1)
#1200
0)
#1205
b10010 ;
1)
#1210
0)
#1215
b10011 ;
1)
#1220
0)
#1225
b10100 ;
1)
#1230
0)
#1235
b10101 ;
1)
#1240
0)
#1245
b10110 ;
1)
#1250
0)
#1255
b10111 ;
1)
#1260
0)
#1265
b11000 ;
1)
#1270
0)
#1275
b11001 ;
1)
#1280
0)
#1285
b11010 ;
1)
#1290
0)
#1295
b11011 ;
1)
#1300
0)
#1305
b11100 ;
1)
#1310
0)
#1315
b11101 ;
1)
#1320
0)
#1325
b11110 ;
1)
#1330
0)
#1335
b11111 ;
1)
#1340
0)
#1345
b100000 ;
1)
#1350
0)
#1355
b100001 ;
1)
#1360
0)
#1365
b100010 ;
1)
#1370
0)
#1375
b100011 ;
1)
#1380
0)
#1385
b100100 ;
1)
#1390
0)
#1395
b100101 ;
1)
#1400
0)
#1405
b100110 ;
1)
#1410
0)
#1415
b100111 ;
1)
#1420
0)
#1425
b101000 ;
1)
#1430
0)
#1435
b101001 ;
1)
#1440
0)
#1445
b101010 ;
1)
#1450
0)
#1455
b101011 ;
1)
#1460
0)
#1465
b101100 ;
1)
#1470
0)
#1475
b101101 ;
1)
#1480
0)
#1485
b101110 ;
1)
#1490
0)
#1495
b101111 ;
1)
#1500
0)
#1505
b110000 ;
1)
#1510
0)
#1515
b110001 ;
1)
#1520
0)
#1525
b110010 ;
1)
#1530
0)
#1535
b110011 ;
1)
#1540
0)
#1545
b110100 ;
1)
#1550
0)
#1555
b110101 ;
1)
#1560
0)
#1565
b110110 ;
1)
#1570
0)
#1575
b110111 ;
1)
#1580
0)
#1585
b111000 ;
1)
#1590
0)
#1595
b111001 ;
1)
#1600
0)
#1605
b111010 ;
1)
#1610
0)
#1615
b111011 ;
1)
#1620
0)
#1625
b111100 ;
1)
#1630
0)
#1635
b111101 ;
1)
#1640
0)
#1645
b111110 ;
1)
#1650
0)
#1655
b111111 ;
1)
#1660
0)
#1665
b1000000 ;
1)
#1670
0)
#1675
b1000001 ;
1)
#1680
0)
#1685
b1000010 ;
1)
#1690
0)
#1695
b1000011 ;
1)
#1700
0)
#1705
b1000100 ;
1)
#1710
0)
#1715
b1000101 ;
1)
#1720
0)
#1725
b1000110 ;
1)
#1730
0)
#1735
b1000111 ;
1)
#1740
0)
#1745
b1001000 ;
1)
#1750
0)
#1755
b1001001 ;
1)
#1760
0)
#1765
b1001010 ;
1)
#1770
0)
#1775
b1001011 ;
1)
#1780
0)
#1785
b1001100 ;
1)
#1790
0)
#1795
b1001101 ;
1)
#1800
0)
#1805
b1001110 ;
1)
#1810
0)
#1815
b1001111 ;
1)
#1820
0)
#1825
b1010000 ;
1)
#1830
0)
#1835
b1010001 ;
1)
#1840
0)
#1845
b1010010 ;
1)
#1850
0)
#1855
b1010011 ;
1)
#1860
0)
#1865
b1010100 ;
1)
#1870
0)
#1875
b1010101 ;
1)
#1880
0)
#1885
b1010110 ;
1)
#1890
0)
#1895
b1010111 ;
1)
#1900
0)
#1905
b1011000 ;
1)
#1910
0)
#1915
b1011001 ;
1)
#1920
0)
#1925
b1011010 ;
1)
#1930
0)
#1935
b1011011 ;
1)
#1940
0)
#1945
b1011100 ;
1)
#1950
0)
#1955
b1011101 ;
1)
#1960
0)
#1965
b1011110 ;
1)
#1970
0)
#1975
b1011111 ;
1)
#1980
0)
#1985
b1100000 ;
1)
#1990
0)
#1995
b1100001 ;
1)
#2000
0)
#2005
b1100010 ;
1)
#2010
0)
#2015
b1100011 ;
1)
#2020
0)
#2025
b1100100 ;
1)
#2030
0)
#2035
b11111111 0
b11111111 !
b11111111 <
b11 7
b1101 #
b1101 9
b10 8
b0 ;
b1010 =
1)
#2040
0)
#2045
b1 ;
1)
#2050
0)
#2055
b10 ;
1)
#2060
0)
#2065
b11 ;
1)
#2070
0)
#2075
b100 ;
1)
#2080
0)
#2085
b101 ;
1)
#2090
0)
#2095
b110 ;
1)
#2100
0)
#2105
b111 ;
1)
#2110
0)
#2115
b1000 ;
1)
#2120
0)
#2125
b1001 ;
1)
#2130
0)
#2135
b1010 ;
1)
#2140
0)
#2145
b1011 ;
1)
#2150
0)
#2155
b1100 ;
1)
#2160
0)
#2165
b1101 ;
1)
#2170
0)
#2175
b1110 ;
1)
#2180
0)
#2185
b1111 ;
1)
#2190
0)
#2195
b10000 ;
1)
#2200
0)
#2205
b10001 ;
1)
#2210
0)
#2215
b10010 ;
1)
#2220
0)
#2225
b10011 ;
1)
#2230
0)
#2235
b10100 ;
1)
#2240
0)
#2245
b10101 ;
1)
#2250
0)
#2255
b10110 ;
1)
#2260
0)
#2265
b10111 ;
1)
#2270
0)
#2275
b11000 ;
1)
#2280
0)
#2285
b11001 ;
1)
#2290
0)
#2295
b11010 ;
1)
#2300
0)
#2305
b11011 ;
1)
#2310
0)
#2315
b11100 ;
1)
#2320
0)
#2325
b11101 ;
1)
#2330
0)
#2335
b11110 ;
1)
#2340
0)
#2345
b11111 ;
1)
#2350
0)
#2355
b100000 ;
1)
#2360
0)
#2365
b100001 ;
1)
#2370
0)
#2375
b100010 ;
1)
#2380
0)
#2385
b100011 ;
1)
#2390
0)
#2395
b100100 ;
1)
#2400
0)
#2405
b100101 ;
1)
#2410
0)
#2415
b100110 ;
1)
#2420
0)
#2425
b100111 ;
1)
#2430
0)
#2435
b101000 ;
1)
#2440
0)
#2445
b101001 ;
1)
#2450
0)
#2455
b101010 ;
1)
#2460
0)
#2465
b101011 ;
1)
#2470
0)
#2475
b101100 ;
1)
#2480
0)
#2485
b101101 ;
1)
#2490
0)
#2495
b101110 ;
1)
#2500
0)
#2505
b101111 ;
1)
#2510
0)
#2515
b110000 ;
1)
#2520
0)
#2525
b110001 ;
1)
#2530
0)
#2535
b110010 ;
1)
#2540
0)
#2545
b110011 ;
1)
#2550
0)
#2555
b110100 ;
1)
#2560
0)
#2565
b110101 ;
1)
#2570
0)
#2575
b110110 ;
1)
#2580
0)
#2585
b110111 ;
1)
#2590
0)
#2595
b111000 ;
1)
#2600
0)
#2605
b111001 ;
1)
#2610
0)
#2615
b111010 ;
1)
#2620
0)
#2625
b111011 ;
1)
#2630
0)
#2635
b111100 ;
1)
#2640
0)
#2645
b111101 ;
1)
#2650
0)
#2655
b111110 ;
1)
#2660
0)
#2665
b111111 ;
1)
#2670
0)
#2675
b1000000 ;
1)
#2680
0)
#2685
b1000001 ;
1)
#2690
0)
#2695
b1000010 ;
1)
#2700
0)
#2705
b1000011 ;
1)
#2710
0)
#2715
b1000100 ;
1)
#2720
0)
#2725
b1000101 ;
1)
#2730
0)
#2735
b1000110 ;
1)
#2740
0)
#2745
b1000111 ;
1)
#2750
0)
#2755
b1001000 ;
1)
#2760
0)
#2765
b1001001 ;
1)
#2770
0)
#2775
b1001010 ;
1)
#2780
0)
#2785
b1001011 ;
1)
#2790
0)
#2795
b1001100 ;
1)
#2800
0)
#2805
b1001101 ;
1)
#2810
0)
#2815
b1001110 ;
1)
#2820
0)
#2825
b1001111 ;
1)
#2830
0)
#2835
b1010000 ;
1)
#2840
0)
#2845
b1010001 ;
1)
#2850
0)
#2855
b1010010 ;
1)
#2860
0)
#2865
b1010011 ;
1)
#2870
0)
#2875
b1010100 ;
1)
#2880
0)
#2885
b1010101 ;
1)
#2890
0)
#2895
b1010110 ;
1)
#2900
0)
#2905
b1010111 ;
1)
#2910
0)
#2915
b1011000 ;
1)
#2920
0)
#2925
b1011001 ;
1)
#2930
0)
#2935
b1011010 ;
1)
#2940
0)
#2945
b1011011 ;
1)
#2950
0)
#2955
b1011100 ;
1)
#2960
0)
#2965
b1011101 ;
1)
#2970
0)
#2975
b1011110 ;
1)
#2980
0)
#2985
b1011111 ;
1)
#2990
0)
#2995
b1100000 ;
1)
#3000
0)
#3005
b1100001 ;
1)
#3010
0)
#3015
b1100010 ;
1)
#3020
0)
#3025
b1100011 ;
1)
#3030
0)
#3035
b1100100 ;
1)
#3040
0)
#3045
b10110000 0
b10110000 !
b10110000 <
b101 7
b1011 #
b1011 9
b11 8
b0 ;
b11 =
1)
#3050
0)
#3055
b1 ;
1)
#3060
0)
#3065
b10 ;
1)
#3070
0)
#3075
b11 ;
1)
#3080
0)
#3085
b100 ;
1)
#3090
0)
#3095
b101 ;
1)
#3100
0)
#3105
b110 ;
1)
#3110
0)
#3115
b111 ;
1)
#3120
0)
#3125
b1000 ;
1)
#3130
0)
#3135
b1001 ;
1)
#3140
0)
#3145
b1010 ;
1)
#3150
0)
#3155
b1011 ;
1)
#3160
0)
#3165
b1100 ;
1)
#3170
0)
#3175
b1101 ;
1)
#3180
0)
#3185
b1110 ;
1)
#3190
0)
#3195
b1111 ;
1)
#3200
0)
#3205
b10000 ;
1)
#3210
0)
#3215
b10001 ;
1)
#3220
0)
#3225
b10010 ;
1)
#3230
0)
#3235
b10011 ;
1)
#3240
0)
#3245
b10100 ;
1)
#3250
0)
#3255
b10101 ;
1)
#3260
0)
#3265
b10110 ;
1)
#3270
0)
#3275
b10111 ;
1)
#3280
0)
#3285
b11000 ;
1)
#3290
0)
#3295
b11001 ;
1)
#3300
0)
#3305
b11010 ;
1)
#3310
0)
#3315
b11011 ;
1)
#3320
0)
#3325
b11100 ;
1)
#3330
0)
#3335
b11101 ;
1)
#3340
0)
#3345
b11110 ;
1)
#3350
0)
#3355
b11111 ;
1)
#3360
0)
#3365
b100000 ;
1)
#3370
0)
#3375
b100001 ;
1)
#3380
0)
#3385
b100010 ;
1)
#3390
0)
#3395
b100011 ;
1)
#3400
0)
#3405
b100100 ;
1)
#3410
0)
#3415
b100101 ;
1)
#3420
0)
#3425
b100110 ;
1)
#3430
0)
#3435
b100111 ;
1)
#3440
0)
#3445
b101000 ;
1)
#3450
0)
#3455
b101001 ;
1)
#3460
0)
#3465
b101010 ;
1)
#3470
0)
#3475
b101011 ;
1)
#3480
0)
#3485
b101100 ;
1)
#3490
0)
#3495
b101101 ;
1)
#3500
0)
#3505
b101110 ;
1)
#3510
0)
#3515
b101111 ;
1)
#3520
0)
#3525
b110000 ;
1)
#3530
0)
#3535
b110001 ;
1)
#3540
0)
#3545
b110010 ;
1)
#3550
0)
#3555
b110011 ;
1)
#3560
0)
#3565
b110100 ;
1)
#3570
0)
#3575
b110101 ;
1)
#3580
0)
#3585
b110110 ;
1)
#3590
0)
#3595
b110111 ;
1)
#3600
0)
#3605
b111000 ;
1)
#3610
0)
#3615
b111001 ;
1)
#3620
0)
#3625
b111010 ;
1)
#3630
0)
#3635
b111011 ;
1)
#3640
0)
#3645
b111100 ;
1)
#3650
0)
#3655
b111101 ;
1)
#3660
0)
#3665
b111110 ;
1)
#3670
0)
#3675
b111111 ;
1)
#3680
0)
#3685
b1000000 ;
1)
#3690
0)
#3695
b1000001 ;
1)
#3700
0)
#3705
b1000010 ;
1)
#3710
0)
#3715
b1000011 ;
1)
#3720
0)
#3725
b1000100 ;
1)
#3730
0)
#3735
b1000101 ;
1)
#3740
0)
#3745
b1000110 ;
1)
#3750
0)
#3755
b1000111 ;
1)
#3760
0)
#3765
b1001000 ;
1)
#3770
0)
#3775
b1001001 ;
1)
#3780
0)
#3785
b1001010 ;
1)
#3790
0)
#3795
b1001011 ;
1)
#3800
0)
#3805
b1001100 ;
1)
#3810
0)
#3815
b1001101 ;
1)
#3820
0)
#3825
b1001110 ;
1)
#3830
0)
#3835
b1001111 ;
1)
#3840
0)
#3845
b1010000 ;
1)
#3850
0)
#3855
b1010001 ;
1)
#3860
0)
#3865
b1010010 ;
1)
#3870
0)
#3875
b1010011 ;
1)
#3880
0)
#3885
b1010100 ;
1)
#3890
0)
#3895
b1010101 ;
1)
#3900
0)
#3905
b1010110 ;
1)
#3910
0)
#3915
b1010111 ;
1)
#3920
0)
#3925
b1011000 ;
1)
#3930
0)
#3935
b1011001 ;
1)
#3940
0)
#3945
b1011010 ;
1)
#3950
0)
#3955
b1011011 ;
1)
#3960
0)
#3965
b1011100 ;
1)
#3970
0)
#3975
b1011101 ;
1)
#3980
0)
#3985
b1011110 ;
1)
#3990
0)
#3995
b1011111 ;
1)
#4000
0)
#4005
b1100000 ;
1)
#4010
0)
#4015
b1100001 ;
1)
#4020
0)
#4025
b1100010 ;
1)
#4030
0)
#4035
b1100011 ;
1)
#4040
0)
#4045
b1100100 ;
1)
