Sensor_interface/Sensor_interface.v
module Sensor_interface #(
    parameter DEBOUNCE_DELAY = 5 // Debounce delay in clock cycles (reduced for simulation)
)(
    // Clock and reset
    input wire clk,                // System clock
    input wire reset,              // Synchronous reset, active high
    
    // Raw sensor inputs
    input wire raw_entry_sensor,   // Raw signal from entry sensor
    input wire raw_exit_sensor,    // Raw signal from exit sensor
    
    // Processed sensor outputs
    output reg entry_sensor,       // Debounced entry sensor signal
    output reg exit_sensor,        // Debounced exit sensor signal
    output reg entry_passed,       // Signal indicating vehicle has fully entered
    output reg exit_passed         // Signal indicating vehicle has fully exited
);

    // Internal registers for debouncing
    reg [7:0] entry_counter;       // Counter for entry sensor debouncing (reduced size)
    reg [7:0] exit_counter;        // Counter for exit sensor debouncing (reduced size)
    reg entry_detected;            // Flag for entry detection
    reg exit_detected;             // Flag for exit detection
    reg entry_sensor_prev;         // Previous state of entry sensor
    reg exit_sensor_prev;          // Previous state of exit sensor
    
    // For simulation debugging
    reg entry_passed_debug;        // Debug signal
    reg exit_passed_debug;         // Debug signal
    
    // Initialize signals
    initial begin
        entry_sensor = 1'b0;
        exit_sensor = 1'b0;
        entry_passed = 1'b0;
        exit_passed = 1'b0;
        entry_counter = 8'h0;
        exit_counter = 8'h0;
        entry_detected = 1'b0;
        exit_detected = 1'b0;
        entry_sensor_prev = 1'b0;
        exit_sensor_prev = 1'b0;
        entry_passed_debug = 1'b0;
        exit_passed_debug = 1'b0;
    end
    
    // Debounce logic for entry sensor - simplified for simulation
    always @(posedge clk) begin
        if (reset) begin
            entry_counter <= 8'h0;
            entry_sensor <= 1'b0;
        end
        else begin
            if (raw_entry_sensor != entry_sensor) begin
                // If the input is different from the current stable value
                if (entry_counter >= DEBOUNCE_DELAY) begin
                    // Counter reached threshold, update the stable output
                    entry_sensor <= raw_entry_sensor;
                    entry_counter <= 8'h0;
                end
                else begin
                    // Increment counter
                    entry_counter <= entry_counter + 1;
                end
            end
            else begin
                // Input matches stable output, reset counter
                entry_counter <= 8'h0;
            end
        end
    end
    
    // Debounce logic for exit sensor - simplified for simulation
    always @(posedge clk) begin
        if (reset) begin
            exit_counter <= 8'h0;
            exit_sensor <= 1'b0;
        end
        else begin
            if (raw_exit_sensor != exit_sensor) begin
                // If the input is different from the current stable value
                if (exit_counter >= DEBOUNCE_DELAY) begin
                    // Counter reached threshold, update the stable output
                    exit_sensor <= raw_exit_sensor;
                    exit_counter <= 8'h0;
                end
                else begin
                    // Increment counter
                    exit_counter <= exit_counter + 1;
                end
            end
            else begin
                // Input matches stable output, reset counter
                exit_counter <= 8'h0;
            end
        end
    end
    
    // Vehicle passage detection logic
    always @(posedge clk) begin
        if (reset) begin
            entry_passed <= 1'b0;
            exit_passed <= 1'b0;
            entry_detected <= 1'b0;
            exit_detected <= 1'b0;
            entry_sensor_prev <= 1'b0;
            exit_sensor_prev <= 1'b0;
            entry_passed_debug <= 1'b0;
            exit_passed_debug <= 1'b0;
        end
        else begin
            // Store previous sensor states
            entry_sensor_prev <= entry_sensor;
            exit_sensor_prev <= exit_sensor;
            
            // Default values - reset after one cycle
            entry_passed <= 1'b0;
            exit_passed <= 1'b0;
            
            // Entry detection logic - simplified for simulation
            if (entry_sensor && !entry_sensor_prev) begin
                // Rising edge of entry sensor - vehicle detected
                entry_detected <= 1'b1;
            end
            else if (!entry_sensor && entry_sensor_prev && entry_detected) begin
                // Falling edge of entry sensor after detection - vehicle has passed
                entry_detected <= 1'b0;
                entry_passed <= 1'b1;
                entry_passed_debug <= 1'b1;  // For debugging
            end
            
            // Exit detection logic - simplified for simulation
            if (exit_sensor && !exit_sensor_prev) begin
                // Rising edge of exit sensor - vehicle detected
                exit_detected <= 1'b1;
            end
            else if (!exit_sensor && exit_sensor_prev && exit_detected) begin
                // Falling edge of exit sensor after detection - vehicle has passed
                exit_detected <= 1'b0;
                exit_passed <= 1'b1;
                exit_passed_debug <= 1'b1;  // For debugging
            end
            
            // Additional direct detection for simulation
            if (raw_entry_sensor == 1'b0 && entry_sensor_prev == 1'b1) begin
                entry_passed <= 1'b1;
            end
            
            if (raw_exit_sensor == 1'b0 && exit_sensor_prev == 1'b1) begin
                exit_passed <= 1'b1;
            end
        end
    end
    
endmodule

Sensor_interface/Sensor_interface_tb.v
module Sensor_interface_tb;
    // Parameters
    parameter CLK_PERIOD = 10;       // Clock period in ns
    parameter DEBOUNCE_DELAY = 5;    // Debounce delay in clock cycles (same as in DUT)
    
    // Testbench signals
    reg clk;
    reg reset;
    reg raw_entry_sensor;
    reg raw_exit_sensor;
    
    wire entry_sensor;
    wire exit_sensor;
    wire entry_passed;
    wire exit_passed;
    
    // Flags for monitoring passed signals
    reg entry_passed_detected;
    reg exit_passed_detected;
    
    // Instantiate the Unit Under Test (UUT)
    Sensor_interface #(
        .DEBOUNCE_DELAY(DEBOUNCE_DELAY)
    ) uut (
        .clk(clk),
        .reset(reset),
        .raw_entry_sensor(raw_entry_sensor),
        .raw_exit_sensor(raw_exit_sensor),
        .entry_sensor(entry_sensor),
        .exit_sensor(exit_sensor),
        .entry_passed(entry_passed),
        .exit_passed(exit_passed)
    );
    
    // VCD file generation for GTKWave
    initial begin
        $dumpfile("sensor_interface_waveform.vcd");
        $dumpvars(0, Sensor_interface_tb);
    end
    
    // Clock generation
    initial begin
        clk = 0;
        forever #(CLK_PERIOD/2) clk = ~clk;
    end
    
    // Monitor for entry_passed and exit_passed signals
    always @(posedge clk) begin
        if (entry_passed) begin
            entry_passed_detected = 1;
            $display("Time=%0t: ENTRY PASSED detected", $time);
        end
        
        if (exit_passed) begin
            exit_passed_detected = 1;
            $display("Time=%0t: EXIT PASSED detected", $time);
        end
    end
    
    // Task for simulating a vehicle entering
    task simulate_vehicle_entry;
        begin
            // Reset detection flag
            entry_passed_detected = 0;
            
            $display("\n=== Simulating Vehicle Entry ===");
            // Vehicle approaches entry sensor
            raw_entry_sensor = 1;
            #(CLK_PERIOD * (DEBOUNCE_DELAY + 2));
            
            // Check if entry sensor is activated
            if (entry_sensor)
                $display("PASS: Entry sensor activated after debounce delay");
            else
                $display("FAIL: Entry sensor not activated");
                
            // Vehicle passes through entry sensor
            #(CLK_PERIOD * 10); // Vehicle takes time to pass
            raw_entry_sensor = 0;
            #(CLK_PERIOD * (DEBOUNCE_DELAY + 10)); // Wait longer for signal to propagate
            
            // Check if entry_passed was detected at any point
            if (entry_passed_detected)
                $display("PASS: entry_passed signal was triggered");
            else
                $display("FAIL: entry_passed signal was not triggered");
                
            // Wait for signals to settle
            #(CLK_PERIOD * 5);
        end
    endtask
    
    // Task for simulating a vehicle exiting
    task simulate_vehicle_exit;
        begin
            // Reset detection flag
            exit_passed_detected = 0;
            
            $display("\n=== Simulating Vehicle Exit ===");
            // Vehicle approaches exit sensor
            raw_exit_sensor = 1;
            #(CLK_PERIOD * (DEBOUNCE_DELAY + 2));
            
            // Check if exit sensor is activated
            if (exit_sensor)
                $display("PASS: Exit sensor activated after debounce delay");
            else
                $display("FAIL: Exit sensor not activated");
                
            // Vehicle passes through exit sensor
            #(CLK_PERIOD * 10); // Vehicle takes time to pass
            raw_exit_sensor = 0;
            #(CLK_PERIOD * (DEBOUNCE_DELAY + 10)); // Wait longer for signal to propagate
            
            // Check if exit_passed was detected at any point
            if (exit_passed_detected)
                $display("PASS: exit_passed signal was triggered");
            else
                $display("FAIL: exit_passed signal was not triggered");
                
            // Wait for signals to settle
            #(CLK_PERIOD * 5);
        end
    endtask
    
    // Task for testing noise rejection
    task test_noise_rejection;
        input is_entry; // 1 for entry sensor, 0 for exit sensor
        begin
            if (is_entry)
                $display("\n=== Testing Entry Sensor Noise Rejection ===");
            else
                $display("\n=== Testing Exit Sensor Noise Rejection ===");
                
            // Apply short pulses (noise)
            for (integer i = 0; i < 3; i = i + 1) begin
                if (is_entry)
                    raw_entry_sensor = 1;
                else
                    raw_exit_sensor = 1;
                    
                #(CLK_PERIOD);
                
                if (is_entry)
                    raw_entry_sensor = 0;
                else
                    raw_exit_sensor = 0;
                    
                #(CLK_PERIOD);
            end
            
            // Check if sensors remained inactive (noise rejected)
            #(CLK_PERIOD);
            if (is_entry) begin
                if (!entry_sensor)
                    $display("PASS: Entry sensor rejected noise");
                else
                    $display("FAIL: Entry sensor activated by noise");
            end else begin
                if (!exit_sensor)
                    $display("PASS: Exit sensor rejected noise");
                else
                    $display("FAIL: Exit sensor activated by noise");
            end
            
            #(CLK_PERIOD * 2);
        end
    endtask
    
    // Task for testing reset functionality
    task test_reset;
        begin
            $display("\n=== Testing Reset Functionality ===");
            
            // Activate both sensors
            raw_entry_sensor = 1;
            raw_exit_sensor = 1;
            #(CLK_PERIOD * (DEBOUNCE_DELAY + 2));
            
            // Verify sensors are active
            if (entry_sensor && exit_sensor)
                $display("Sensors activated successfully before reset");
            
            // Apply reset
            reset = 1;
            #(CLK_PERIOD * 2);
            reset = 0;
            #(CLK_PERIOD);
            
            // Check if all outputs are reset
            if (!entry_sensor && !exit_sensor && !entry_passed && !exit_passed)
                $display("PASS: All outputs reset to 0");
            else
                $display("FAIL: Not all outputs reset to 0");
                
            // Return to inactive state
            raw_entry_sensor = 0;
            raw_exit_sensor = 0;
            #(CLK_PERIOD * 5);
        end
    endtask
    
    // Task for testing simultaneous entry and exit
    task test_simultaneous_entry_exit;
        begin
            // Reset detection flags
            entry_passed_detected = 0;
            exit_passed_detected = 0;
            
            $display("\n=== Testing Simultaneous Entry and Exit ===");
            
            // Activate both sensors
            raw_entry_sensor = 1;
            raw_exit_sensor = 1;
            #(CLK_PERIOD * (DEBOUNCE_DELAY + 2));
            
            // Check if both sensors are activated
            if (entry_sensor && exit_sensor)
                $display("PASS: Both sensors activated simultaneously");
            else
                $display("FAIL: Both sensors not activated");
                
            // Both vehicles pass through sensors
            #(CLK_PERIOD * 10);
            raw_entry_sensor = 0;
            raw_exit_sensor = 0;
            #(CLK_PERIOD * (DEBOUNCE_DELAY + 10)); // Wait longer for signals to propagate
            
            // Check if both passed signals were detected at any point
            if (entry_passed_detected && exit_passed_detected)
                $display("PASS: Both entry_passed and exit_passed signals were triggered");
            else
                $display("FAIL: Both passed signals were not triggered");
                
            #(CLK_PERIOD * 5);
        end
    endtask
    
    // Task for testing rapid sensor toggling (stress test)
    task test_rapid_toggling;
        input is_entry; // 1 for entry sensor, 0 for exit sensor
        begin
            if (is_entry)
                $display("\n=== Testing Rapid Entry Sensor Toggling ===");
            else
                $display("\n=== Testing Rapid Exit Sensor Toggling ===");
                
            // Rapidly toggle the sensor
            for (integer i = 0; i < 10; i = i + 1) begin
                if (is_entry)
                    raw_entry_sensor = ~raw_entry_sensor;
                else
                    raw_exit_sensor = ~raw_exit_sensor;
                    
                #(CLK_PERIOD);
            end
            
            // Let the debounce logic stabilize
            #(CLK_PERIOD * (DEBOUNCE_DELAY + 5));
            
            // Return to inactive state
            if (is_entry)
                raw_entry_sensor = 0;
            else
                raw_exit_sensor = 0;
                
            #(CLK_PERIOD * 5);
            $display("Rapid toggling test completed - check waveform for proper debouncing");
        end
    endtask
    
    // Main test sequence
    initial begin
        // Initialize inputs and flags
        reset = 1;
        raw_entry_sensor = 0;
        raw_exit_sensor = 0;
        entry_passed_detected = 0;
        exit_passed_detected = 0;
        
        // Apply reset
        #(CLK_PERIOD*2);
        reset = 0;
        #(CLK_PERIOD*5);
        
        $display("=== Starting Sensor Interface Tests ===");
        
        // Test 1: Noise rejection for entry sensor
        test_noise_rejection(1);
        
        // Test 2: Noise rejection for exit sensor
        test_noise_rejection(0);
        
        // Test 3: Normal vehicle entry
        simulate_vehicle_entry();
        
        // Test 4: Normal vehicle exit
        simulate_vehicle_exit();
        
        // Test 5: Reset functionality
        test_reset();
        
        // Test 6: Simultaneous entry and exit
        test_simultaneous_entry_exit();
        
        // Test 7: Rapid toggling of entry sensor
        test_rapid_toggling(1);
        
        // Test 8: Rapid toggling of exit sensor
        test_rapid_toggling(0);
        
        // End simulation
        #(CLK_PERIOD*10);
        $display("\n=== Sensor Interface Tests Completed Successfully ===");
        $finish;
    end
    
endmodule

Sensor_interface/sensor_interface_waveform.vcd
$date
	Mon Jun 16 13:19:42 2025
$end
$version
	Icarus Verilog
$end
$timescale
	1s
$end
$scope module Sensor_interface_tb $end
$var wire 1 ! exit_sensor $end
$var wire 1 " exit_passed $end
$var wire 1 # entry_sensor $end
$var wire 1 $ entry_passed $end
$var parameter 32 % CLK_PERIOD $end
$var parameter 32 & DEBOUNCE_DELAY $end
$var reg 1 ' clk $end
$var reg 1 ( entry_passed_detected $end
$var reg 1 ) exit_passed_detected $end
$var reg 1 * raw_entry_sensor $end
$var reg 1 + raw_exit_sensor $end
$var reg 1 , reset $end
$scope module uut $end
$var wire 1 ' clk $end
$var wire 1 * raw_entry_sensor $end
$var wire 1 + raw_exit_sensor $end
$var wire 1 , reset $end
$var parameter 32 - DEBOUNCE_DELAY $end
$var reg 8 . entry_counter [7:0] $end
$var reg 1 / entry_detected $end
$var reg 1 $ entry_passed $end
$var reg 1 0 entry_passed_debug $end
$var reg 1 # entry_sensor $end
$var reg 1 1 entry_sensor_prev $end
$var reg 8 2 exit_counter [7:0] $end
$var reg 1 3 exit_detected $end
$var reg 1 " exit_passed $end
$var reg 1 4 exit_passed_debug $end
$var reg 1 ! exit_sensor $end
$var reg 1 5 exit_sensor_prev $end
$upscope $end
$scope task simulate_vehicle_entry $end
$upscope $end
$scope task simulate_vehicle_exit $end
$upscope $end
$scope task test_noise_rejection $end
$var reg 1 6 is_entry $end
$scope begin $ivl_for_loop0 $end
$var integer 32 7 i [31:0] $end
$upscope $end
$upscope $end
$scope task test_rapid_toggling $end
$var reg 1 8 is_entry $end
$scope begin $ivl_for_loop1 $end
$var integer 32 9 i [31:0] $end
$upscope $end
$upscope $end
$scope task test_reset $end
$upscope $end
$scope task test_simultaneous_entry_exit $end
$upscope $end
$upscope $end
$enddefinitions $end
$comment Show the parameter values. $end
$dumpall
b101 -
b101 &
b1010 %
$end
#0
$dumpvars
bx 9
x8
bx 7
x6
05
04
03
b0 2
01
00
0/
b0 .
1,
0+
0*
0)
0(
0'
0$
0#
0"
0!
$end
#5
1'
#10
0'
#15
1'
#20
0'
0,
#25
1'
#30
0'
#35
1'
#40
0'
#45
1'
#50
0'
#55
1'
#60
0'
#65
1'
#70
0'
1*
b0 7
16
#75
b1 .
1'
#80
0'
0*
#85
b0 .
1'
#90
0'
1*
b1 7
#95
b1 .
1'
#100
0'
0*
#105
b0 .
1'
#110
0'
1*
b10 7
#115
b1 .
1'
#120
0'
0*
#125
b0 .
1'
#130
0'
b11 7
#135
1'
#140
0'
#145
1'
#150
0'
#155
1'
#160
0'
1+
b0 7
06
#165
b1 2
1'
#170
0'
0+
#175
b0 2
1'
#180
0'
1+
b1 7
#185
b1 2
1'
#190
0'
0+
#195
b0 2
1'
#200
0'
1+
b10 7
#205
b1 2
1'
#210
0'
0+
#215
b0 2
1'
#220
0'
b11 7
#225
1'
#230
0'
#235
1'
#240
0'
#245
1'
#250
0'
1*
#255
b1 .
1'
#260
0'
#265
b10 .
1'
#270
0'
#275
b11 .
1'
#280
0'
#285
b100 .
1'
#290
0'
#295
b101 .
1'
#300
0'
#305
b0 .
1#
1'
#310
0'
#315
1/
11
1'
#320
0'
#325
1'
#330
0'
#335
1'
#340
0'
#345
1'
#350
0'
#355
1'
#360
0'
#365
1'
#370
0'
#375
1'
#380
0'
#385
1'
#390
0'
#395
1'
#400
0'
#405
1'
#410
0'
#415
1'
#420
0'
0*
#425
b1 .
1$
1'
#430
0'
#435
1$
b10 .
1(
1'
#440
0'
#445
b11 .
1$
1'
#450
0'
#455
1$
b100 .
1'
#460
0'
#465
b101 .
1$
1'
#470
0'
#475
1$
b0 .
0#
1'
#480
0'
#485
10
0/
1$
01
1'
#490
0'
#495
0$
1'
#500
0'
#505
1'
#510
0'
#515
1'
#520
0'
#525
1'
#530
0'
#535
1'
#540
0'
#545
1'
#550
0'
#555
1'
#560
0'
#565
1'
#570
0'
#575
1'
#580
0'
#585
1'
#590
0'
#595
1'
#600
0'
#605
1'
#610
0'
#615
1'
#620
0'
1+
#625
b1 2
1'
#630
0'
#635
b10 2
1'
#640
0'
#645
b11 2
1'
#650
0'
#655
b100 2
1'
#660
0'
#665
b101 2
1'
#670
0'
#675
b0 2
1!
1'
#680
0'
#685
13
15
1'
#690
0'
#695
1'
#700
0'
#705
1'
#710
0'
#715
1'
#720
0'
#725
1'
#730
0'
#735
1'
#740
0'
#745
1'
#750
0'
#755
1'
#760
0'
#765
1'
#770
0'
#775
1'
#780
0'
#785
1'
#790
0'
0+
#795
1"
b1 2
1'
#800
0'
#805
b10 2
1"
1)
1'
#810
0'
#815
1"
b11 2
1'
#820
0'
#825
b100 2
1"
1'
#830
0'
#835
1"
b101 2
1'
#840
0'
#845
b0 2
0!
1"
1'
#850
0'
#855
14
03
1"
05
1'
#860
0'
#865
0"
1'
#870
0'
#875
1'
#880
0'
#885
1'
#890
0'
#895
1'
#900
0'
#905
1'
#910
0'
#915
1'
#920
0'
#925
1'
#930
0'
#935
1'
#940
0'
#945
1'
#950
0'
#955
1'
#960
0'
#965
1'
#970
0'
#975
1'
#980
0'
#985
1'
#990
0'
1+
1*
#995
b1 2
b1 .
1'
#1000
0'
#1005
b10 .
b10 2
1'
#1010
0'
#1015
b11 2
b11 .
1'
#1020
0'
#1025
b100 .
b100 2
1'
#1030
0'
#1035
b101 2
b101 .
1'
#1040
0'
#1045
b0 .
1#
b0 2
1!
1'
#1050
0'
#1055
13
1/
15
11
1'
#1060
0'
1,
#1065
0#
0!
04
00
05
01
03
0/
1'
#1070
0'
#1075
1'
#1080
0'
0,
#1085
b1 .
b1 2
1'
#1090
0'
0+
0*
#1095
b0 2
b0 .
1'
#1100
0'
#1105
1'
#1110
0'
#1115
1'
#1120
0'
#1125
1'
#1130
0'
#1135
1'
#1140
0'
1+
1*
0)
0(
#1145
b1 .
b1 2
1'
#1150
0'
#1155
b10 2
b10 .
1'
#1160
0'
#1165
b11 .
b11 2
1'
#1170
0'
#1175
b100 2
b100 .
1'
#1180
0'
#1185
b101 .
b101 2
1'
#1190
0'
#1195
b0 2
1!
b0 .
1#
1'
#1200
0'
#1205
13
1/
15
11
1'
#1210
0'
#1215
1'
#1220
0'
#1225
1'
#1230
0'
#1235
1'
#1240
0'
#1245
1'
#1250
0'
#1255
1'
#1260
0'
#1265
1'
#1270
0'
#1275
1'
#1280
0'
#1285
1'
#1290
0'
#1295
1'
#1300
0'
#1305
1'
#1310
0'
0+
0*
#1315
1"
1$
b1 2
b1 .
1'
#1320
0'
#1325
b10 .
b10 2
1"
1$
1)
1(
1'
#1330
0'
#1335
1"
1$
b11 2
b11 .
1'
#1340
0'
#1345
b100 .
b100 2
1"
1$
1'
#1350
0'
#1355
1"
1$
b101 2
b101 .
1'
#1360
0'
#1365
b0 .
0#
b0 2
0!
1"
1$
1'
#1370
0'
#1375
14
03
10
0/
1"
1$
05
01
1'
#1380
0'
#1385
0"
0$
1'
#1390
0'
#1395
1'
#1400
0'
#1405
1'
#1410
0'
#1415
1'
#1420
0'
#1425
1'
#1430
0'
#1435
1'
#1440
0'
#1445
1'
#1450
0'
#1455
1'
#1460
0'
#1465
1'
#1470
0'
#1475
1'
#1480
0'
#1485
1'
#1490
0'
#1495
1'
#1500
0'
#1505
1'
#1510
0'
1*
b0 9
18
#1515
b1 .
1'
#1520
0'
0*
b1 9
#1525
b0 .
1'
#1530
0'
1*
b10 9
#1535
b1 .
1'
#1540
0'
0*
b11 9
#1545
b0 .
1'
#1550
0'
1*
b100 9
#1555
b1 .
1'
#1560
0'
0*
b101 9
#1565
b0 .
1'
#1570
0'
1*
b110 9
#1575
b1 .
1'
#1580
0'
0*
b111 9
#1585
b0 .
1'
#1590
0'
1*
b1000 9
#1595
b1 .
1'
#1600
0'
0*
b1001 9
#1605
b0 .
1'
#1610
0'
b1010 9
#1615
1'
#1620
0'
#1625
1'
#1630
0'
#1635
1'
#1640
0'
#1645
1'
#1650
0'
#1655
1'
#1660
0'
#1665
1'
#1670
0'
#1675
1'
#1680
0'
#1685
1'
#1690
0'
#1695
1'
#1700
0'
#1705
1'
#1710
0'
#1715
1'
#1720
0'
#1725
1'
#1730
0'
#1735
1'
#1740
0'
#1745
1'
#1750
0'
#1755
1'
#1760
0'
1+
b0 9
08
#1765
b1 2
1'
#1770
0'
0+
b1 9
#1775
b0 2
1'
#1780
0'
1+
b10 9
#1785
b1 2
1'
#1790
0'
0+
b11 9
#1795
b0 2
1'
#1800
0'
1+
b100 9
#1805
b1 2
1'
#1810
0'
0+
b101 9
#1815
b0 2
1'
#1820
0'
1+
b110 9
#1825
b1 2
1'
#1830
0'
0+
b111 9
#1835
b0 2
1'
#1840
0'
1+
b1000 9
#1845
b1 2
1'
#1850
0'
0+
b1001 9
#1855
b0 2
1'
#1860
0'
b1010 9
