Vehicle_counter/Vehicle_counter.v
module Vehicle_counter #(
    parameter MAX_CAPACITY = 63  // Maximum parking capacity (6-bit value: 0-63)
)(
    // Clock and reset
    input wire clk,              // System clock
    input wire reset,            // Synchronous reset, active high
    
    // Inputs from Sensor Interface Module
    input wire entry_passed,     // Signal indicating vehicle has entered
    input wire exit_passed,      // Signal indicating vehicle has exited
    
    // Input for configuration
    input wire [5:0] max_capacity, // Configurable maximum capacity
    
    // Outputs
    output reg [5:0] vehicle_count,    // Current number of vehicles in the parking
    output reg [5:0] available_spaces, // Number of available parking spaces
    output reg parking_full            // Signal indicating parking is full
);

    // Initialize signals
    initial begin
        vehicle_count = 6'b000000;
        available_spaces = max_capacity;
        parking_full = 1'b0;
    end
    
    // Main counter logic
    always @(posedge clk or posedge reset) begin
        if (reset) begin
            // Reset counter values
            vehicle_count <= 6'b000000;
            available_spaces <= max_capacity;
            parking_full <= 1'b0;
        end
        else begin
            // Handle vehicle entry
            if (entry_passed && !parking_full) begin
                if (vehicle_count < max_capacity) begin
                    vehicle_count <= vehicle_count + 1'b1;
                    available_spaces <= available_spaces - 1'b1;
                    
                    // Check if parking becomes full after this entry
                    if (vehicle_count + 1'b1 >= max_capacity) begin
                        parking_full <= 1'b1;
                    end
                end
            end
            
            // Handle vehicle exit
            if (exit_passed && vehicle_count > 0) begin
                vehicle_count <= vehicle_count - 1'b1;
                available_spaces <= available_spaces + 1'b1;
                parking_full <= 1'b0; // No longer full after a vehicle exits
            end
        end
    end
    
    // Handle max_capacity changes
    always @(max_capacity) begin
        // Update available spaces based on new max_capacity
        if (vehicle_count <= max_capacity) begin
            available_spaces <= max_capacity - vehicle_count;
        end else begin
            // If current count exceeds new max_capacity
            available_spaces <= 0;
        end
        
        // Update parking_full flag based on new max_capacity
        parking_full <= (vehicle_count >= max_capacity) ? 1'b1 : 1'b0;
    end

endmodule

Vehicle_counter/Vehicle_counter_tb.v
module Vehicle_counter_tb;
    // Parameters
    parameter CLK_PERIOD = 10;       // Clock period in ns
    parameter MAX_CAPACITY = 63;     // Maximum parking capacity (6-bit value)
    
    // Testbench signals
    reg clk;
    reg reset;
    reg entry_passed;
    reg exit_passed;
    reg [5:0] max_capacity;
    
    wire [5:0] vehicle_count;
    wire [5:0] available_spaces;
    wire parking_full;
    
    // Instantiate the Unit Under Test (UUT)
    Vehicle_counter #(
        .MAX_CAPACITY(MAX_CAPACITY)
    ) uut (
        .clk(clk),
        .reset(reset),
        .entry_passed(entry_passed),
        .exit_passed(exit_passed),
        .max_capacity(max_capacity),
        .vehicle_count(vehicle_count),
        .available_spaces(available_spaces),
        .parking_full(parking_full)
    );
    
    // VCD file generation for GTKWave
    initial begin
        $dumpfile("vehicle_counter_waveform.vcd");
        $dumpvars(0, Vehicle_counter_tb);
    end
    
    // Clock generation
    initial begin
        clk = 0;
        forever #(CLK_PERIOD/2) clk = ~clk;
    end
    
    // Task for simulating a vehicle entry
    task simulate_vehicle_entry;
        begin
            $display("\n=== Simulating Vehicle Entry ===");
            entry_passed = 1;
            #(CLK_PERIOD);
            entry_passed = 0;
            #(CLK_PERIOD);
            
            $display("Vehicle entered: count=%0d, available=%0d, full=%0b", 
                    vehicle_count, available_spaces, parking_full);
        end
    endtask
    
    // Task for simulating a vehicle exit
    task simulate_vehicle_exit;
        begin
            $display("\n=== Simulating Vehicle Exit ===");
            exit_passed = 1;
            #(CLK_PERIOD);
            exit_passed = 0;
            #(CLK_PERIOD);
            
            $display("Vehicle exited: count=%0d, available=%0d, full=%0b", 
                    vehicle_count, available_spaces, parking_full);
        end
    endtask
    
    // Task for testing simultaneous entry and exit
    task test_simultaneous_entry_exit;
        begin
            $display("\n=== Testing Simultaneous Entry and Exit ===");
            entry_passed = 1;
            exit_passed = 1;
            #(CLK_PERIOD);
            entry_passed = 0;
            exit_passed = 0;
            #(CLK_PERIOD);
            
            $display("After simultaneous entry/exit: count=%0d, available=%0d, full=%0b", 
                    vehicle_count, available_spaces, parking_full);
        end
    endtask
    
    // Task for testing parking full condition
    task test_parking_full;
        input integer target_count;
        begin
            $display("\n=== Testing Parking Full Condition ===");
            $display("Filling parking to capacity (%0d vehicles)...", target_count);
            
            // Fill parking to the target count
            while (vehicle_count < target_count) begin
                entry_passed = 1;
                #(CLK_PERIOD);
                entry_passed = 0;
                #(CLK_PERIOD);
            end
            
            $display("Parking status: count=%0d, available=%0d, full=%0b", 
                    vehicle_count, available_spaces, parking_full);
                    
            // Try to add one more vehicle when full
            if (parking_full) begin
                $display("Attempting to add vehicle when parking is full...");
                entry_passed = 1;
                #(CLK_PERIOD);
                entry_passed = 0;
                #(CLK_PERIOD);
                
                if (vehicle_count == target_count)
                    $display("PASS: Vehicle entry blocked when parking is full");
                else
                    $display("FAIL: Vehicle count increased despite parking being full");
            end
        end
    endtask
    
    // Task for testing max capacity update
    task test_max_capacity_update;
        input [5:0] new_capacity;
        begin
            $display("\n=== Testing Max Capacity Update ===");
            $display("Changing max_capacity from %0d to %0d", max_capacity, new_capacity);
            
            max_capacity = new_capacity;
            #(CLK_PERIOD*2);
            
            $display("After capacity update: count=%0d, available=%0d, full=%0b", 
                    vehicle_count, available_spaces, parking_full);
                    
            // Check if available spaces updated correctly
            if (vehicle_count <= new_capacity) begin
                // Normal case: vehicle_count is less than or equal to new_capacity
                if (available_spaces == (new_capacity - vehicle_count))
                    $display("PASS: Available spaces updated correctly");
                else
                    $display("FAIL: Available spaces not updated correctly");
            end else begin
                // Edge case: vehicle_count exceeds new_capacity
                if (available_spaces == 0)
                    $display("PASS: Available spaces updated correctly to 0 when vehicle count exceeds capacity");
                else
                    $display("FAIL: Available spaces should be 0 when vehicle count exceeds capacity");
            end
                
            // Check if parking_full flag is set correctly
            if ((vehicle_count >= new_capacity && parking_full) || 
                (vehicle_count < new_capacity && !parking_full))
                $display("PASS: Parking full flag updated correctly");
            else
                $display("FAIL: Parking full flag not updated correctly");
        end
    endtask
    
    // Task for testing reset functionality
    task test_reset;
        begin
            $display("\n=== Testing Reset Functionality ===");
            
            // Apply reset
            reset = 1;
            #(CLK_PERIOD*2);
            reset = 0;
            #(CLK_PERIOD);
            
            // Check if all outputs are reset
            if (vehicle_count == 0 && available_spaces == max_capacity && !parking_full)
                $display("PASS: All outputs reset to initial values");
            else
                $display("FAIL: Not all outputs reset correctly");
        end
    endtask
    
    // Main test sequence
    initial begin
        // Initialize inputs
        reset = 1;
        entry_passed = 0;
        exit_passed = 0;
        max_capacity = MAX_CAPACITY;
        
        // Apply reset
        #(CLK_PERIOD*2);
        reset = 0;
        #(CLK_PERIOD*2);
        
        $display("=== Starting Vehicle Counter Tests ===");
        $display("Initial state: count=%0d, available=%0d, full=%0b", 
                vehicle_count, available_spaces, parking_full);
        
        // Test 1: Single vehicle entry
        simulate_vehicle_entry();
        
        // Test 2: Multiple vehicle entries
        $display("\n=== Testing Multiple Vehicle Entries ===");
        repeat(5) begin
            simulate_vehicle_entry();
        end
        
        // Test 3: Single vehicle exit
        simulate_vehicle_exit();
        
        // Test 4: Multiple vehicle exits
        $display("\n=== Testing Multiple Vehicle Exits ===");
        repeat(3) begin
            simulate_vehicle_exit();
        end
        
        // Test 5: Simultaneous entry and exit
        test_simultaneous_entry_exit();
        
        // Test 6: Filling parking to capacity
        test_parking_full(max_capacity);
        
        // Test 7: Test vehicle exit when parking is full
        $display("\n=== Testing Vehicle Exit When Parking Is Full ===");
        simulate_vehicle_exit();
        
        // Test 8: Changing max capacity to a lower value
        test_max_capacity_update(10);
        
        // Test 9: Changing max capacity to a higher value
        test_max_capacity_update(MAX_CAPACITY);
        
        // Test 10: Reset during operation
        test_reset();
        
        // Test 11: Edge case - try to exit when count is 0
        $display("\n=== Testing Exit When Count is 0 ===");
        simulate_vehicle_exit();
        if (vehicle_count == 0)
            $display("PASS: Count remained at 0 when attempting to exit from empty parking");
        else
            $display("FAIL: Count changed when attempting to exit from empty parking");
        
        // End simulation
        #(CLK_PERIOD*10);
        $display("\n=== Vehicle Counter Tests Completed Successfully ===");
        $finish;
    end
    
    // Monitor for important state changes
    always @(parking_full) begin
        if (parking_full)
            $display("Time=%0t: PARKING FULL FLAG ACTIVATED", $time);
        else if ($time > 0)
            $display("Time=%0t: PARKING FULL FLAG DEACTIVATED", $time);
    end
    
endmodule

Vehicle_counter/vehicle_counter_waveform.vcd
$date
	Mon Jun 16 13:33:39 2025
$end
$version
	Icarus Verilog
$end
$timescale
	1s
$end
$scope module Vehicle_counter_tb $end
$var wire 6 ! vehicle_count [5:0] $end
$var wire 1 " parking_full $end
$var wire 6 # available_spaces [5:0] $end
$var parameter 32 $ CLK_PERIOD $end
$var parameter 32 % MAX_CAPACITY $end
$var reg 1 & clk $end
$var reg 1 ' entry_passed $end
$var reg 1 ( exit_passed $end
$var reg 6 ) max_capacity [5:0] $end
$var reg 1 * reset $end
$scope module uut $end
$var wire 1 & clk $end
$var wire 1 ' entry_passed $end
$var wire 1 ( exit_passed $end
$var wire 6 + max_capacity [5:0] $end
$var wire 1 * reset $end
$var parameter 32 , MAX_CAPACITY $end
$var reg 6 - available_spaces [5:0] $end
$var reg 1 " parking_full $end
$var reg 6 . vehicle_count [5:0] $end
$upscope $end
$scope task simulate_vehicle_entry $end
$upscope $end
$scope task simulate_vehicle_exit $end
$upscope $end
$scope task test_max_capacity_update $end
$var reg 6 / new_capacity [5:0] $end
$upscope $end
$scope task test_parking_full $end
$var integer 32 0 target_count [31:0] $end
$upscope $end
$scope task test_reset $end
$upscope $end
$scope task test_simultaneous_entry_exit $end
$upscope $end
$upscope $end
$enddefinitions $end
$comment Show the parameter values. $end
$dumpall
b111111 ,
b111111 %
b1010 $
$end
#0
$dumpvars
bx 0
bx /
b0 .
b111111 -
b111111 +
1*
b111111 )
0(
0'
0&
b111111 #
0"
b0 !
$end
#5
1&
#10
0&
#15
1&
#20
0&
0*
#25
1&
#30
0&
#35
1&
#40
0&
1'
#45
b111110 #
b111110 -
b1 !
b1 .
1&
#50
0&
0'
#55
1&
#60
0&
1'
#65
b111101 #
b111101 -
b10 !
b10 .
1&
#70
0&
0'
#75
1&
#80
0&
1'
#85
b111100 #
b111100 -
b11 !
b11 .
1&
#90
0&
0'
#95
1&
#100
0&
1'
#105
b111011 #
b111011 -
b100 !
b100 .
1&
#110
0&
0'
#115
1&
#120
0&
1'
#125
b111010 #
b111010 -
b101 !
b101 .
1&
#130
0&
0'
#135
1&
#140
0&
1'
#145
b111001 #
b111001 -
b110 !
b110 .
1&
#150
0&
0'
#155
1&
#160
0&
1(
#165
b111010 #
b111010 -
b101 !
b101 .
1&
#170
0&
0(
#175
1&
#180
0&
1(
#185
b111011 #
b111011 -
b100 !
b100 .
1&
#190
0&
0(
#195
1&
#200
0&
1(
#205
b111100 #
b111100 -
b11 !
b11 .
1&
#210
0&
0(
#215
1&
#220
0&
1(
#225
b111101 #
b111101 -
b10 !
b10 .
1&
#230
0&
0(
#235
1&
#240
0&
1(
1'
#245
b111110 #
b111110 -
b1 !
b1 .
1&
#250
0&
0(
0'
#255
1&
#260
0&
1'
b111111 0
#265
b111101 #
b111101 -
b10 !
b10 .
1&
#270
0&
0'
#275
1&
#280
0&
1'
#285
b111100 #
b111100 -
b11 !
b11 .
1&
#290
0&
0'
#295
1&
#300
0&
1'
#305
b111011 #
b111011 -
b100 !
b100 .
1&
#310
0&
0'
#315
1&
#320
0&
1'
#325
b111010 #
b111010 -
b101 !
b101 .
1&
#330
0&
0'
#335
1&
#340
0&
1'
#345
b111001 #
b111001 -
b110 !
b110 .
1&
#350
0&
0'
#355
1&
#360
0&
1'
#365
b111000 #
b111000 -
b111 !
b111 .
1&
#370
0&
0'
#375
1&
#380
0&
1'
#385
b110111 #
b110111 -
b1000 !
b1000 .
1&
#390
0&
0'
#395
1&
#400
0&
1'
#405
b110110 #
b110110 -
b1001 !
b1001 .
1&
#410
0&
0'
#415
1&
#420
0&
1'
#425
b110101 #
b110101 -
b1010 !
b1010 .
1&
#430
0&
0'
#435
1&
#440
0&
1'
#445
b110100 #
b110100 -
b1011 !
b1011 .
1&
#450
0&
0'
#455
1&
#460
0&
1'
#465
b110011 #
b110011 -
b1100 !
b1100 .
1&
#470
0&
0'
#475
1&
#480
0&
1'
#485
b110010 #
b110010 -
b1101 !
b1101 .
1&
#490
0&
0'
#495
1&
#500
0&
1'
#505
b110001 #
b110001 -
b1110 !
b1110 .
1&
#510
0&
0'
#515
1&
#520
0&
1'
#525
b110000 #
b110000 -
b1111 !
b1111 .
1&
#530
0&
0'
#535
1&
#540
0&
1'
#545
b101111 #
b101111 -
b10000 !
b10000 .
1&
#550
0&
0'
#555
1&
#560
0&
1'
#565
b101110 #
b101110 -
b10001 !
b10001 .
1&
#570
0&
0'
#575
1&
#580
0&
1'
#585
b101101 #
b101101 -
b10010 !
b10010 .
1&
#590
0&
0'
#595
1&
#600
0&
1'
#605
b101100 #
b101100 -
b10011 !
b10011 .
1&
#610
0&
0'
#615
1&
#620
0&
1'
#625
b101011 #
b101011 -
b10100 !
b10100 .
1&
#630
0&
0'
#635
1&
#640
0&
1'
#645
b101010 #
b101010 -
b10101 !
b10101 .
1&
#650
0&
0'
#655
1&
#660
0&
1'
#665
b101001 #
b101001 -
b10110 !
b10110 .
1&
#670
0&
0'
#675
1&
#680
0&
1'
#685
b101000 #
b101000 -
b10111 !
b10111 .
1&
#690
0&
0'
#695
1&
#700
0&
1'
#705
b100111 #
b100111 -
b11000 !
b11000 .
1&
#710
0&
0'
#715
1&
#720
0&
1'
#725
b100110 #
b100110 -
b11001 !
b11001 .
1&
#730
0&
0'
#735
1&
#740
0&
1'
#745
b100101 #
b100101 -
b11010 !
b11010 .
1&
#750
0&
0'
#755
1&
#760
0&
1'
#765
b100100 #
b100100 -
b11011 !
b11011 .
1&
#770
0&
0'
#775
1&
#780
0&
1'
#785
b100011 #
b100011 -
b11100 !
b11100 .
1&
#790
0&
0'
#795
1&
#800
0&
1'
#805
b100010 #
b100010 -
b11101 !
b11101 .
1&
#810
0&
0'
#815
1&
#820
0&
1'
#825
b100001 #
b100001 -
b11110 !
b11110 .
1&
#830
0&
0'
#835
1&
#840
0&
1'
#845
b100000 #
b100000 -
b11111 !
b11111 .
1&
#850
0&
0'
#855
1&
#860
0&
1'
#865
b11111 #
b11111 -
b100000 !
b100000 .
1&
#870
0&
0'
#875
1&
#880
0&
1'
#885
b11110 #
b11110 -
b100001 !
b100001 .
1&
#890
0&
0'
#895
1&
#900
0&
1'
#905
b11101 #
b11101 -
b100010 !
b100010 .
1&
#910
0&
0'
#915
1&
#920
0&
1'
#925
b11100 #
b11100 -
b100011 !
b100011 .
1&
#930
0&
0'
#935
1&
#940
0&
1'
#945
b11011 #
b11011 -
b100100 !
b100100 .
1&
#950
0&
0'
#955
1&
#960
0&
1'
#965
b11010 #
b11010 -
b100101 !
b100101 .
1&
#970
0&
0'
#975
1&
#980
0&
1'
#985
b11001 #
b11001 -
b100110 !
b100110 .
1&
#990
0&
0'
#995
1&
#1000
0&
1'
#1005
b11000 #
b11000 -
b100111 !
b100111 .
1&
#1010
0&
0'
#1015
1&
#1020
0&
1'
#1025
b10111 #
b10111 -
b101000 !
b101000 .
1&
#1030
0&
0'
#1035
1&
#1040
0&
1'
#1045
b10110 #
b10110 -
b101001 !
b101001 .
1&
#1050
0&
0'
#1055
1&
#1060
0&
1'
#1065
b10101 #
b10101 -
b101010 !
b101010 .
1&
#1070
0&
0'
#1075
1&
#1080
0&
1'
#1085
b10100 #
b10100 -
b101011 !
b101011 .
1&
#1090
0&
0'
#1095
1&
#1100
0&
1'
#1105
b10011 #
b10011 -
b101100 !
b101100 .
1&
#1110
0&
0'
#1115
1&
#1120
0&
1'
#1125
b10010 #
b10010 -
b101101 !
b101101 .
1&
#1130
0&
0'
#1135
1&
#1140
0&
1'
#1145
b10001 #
b10001 -
b101110 !
b101110 .
1&
#1150
0&
0'
#1155
1&
#1160
0&
1'
#1165
b10000 #
b10000 -
b101111 !
b101111 .
1&
#1170
0&
0'
#1175
1&
#1180
0&
1'
#1185
b1111 #
b1111 -
b110000 !
b110000 .
1&
#1190
0&
0'
#1195
1&
#1200
0&
1'
#1205
b1110 #
b1110 -
b110001 !
b110001 .
1&
#1210
0&
0'
#1215
1&
#1220
0&
1'
#1225
b1101 #
b1101 -
b110010 !
b110010 .
1&
#1230
0&
0'
#1235
1&
#1240
0&
1'
#1245
b1100 #
b1100 -
b110011 !
b110011 .
1&
#1250
0&
0'
#1255
1&
#1260
0&
1'
#1265
b1011 #
b1011 -
b110100 !
b110100 .
1&
#1270
0&
0'
#1275
1&
#1280
0&
1'
#1285
b1010 #
b1010 -
b110101 !
b110101 .
1&
#1290
0&
0'
#1295
1&
#1300
0&
1'
#1305
b1001 #
b1001 -
b110110 !
b110110 .
1&
#1310
0&
0'
#1315
1&
#1320
0&
1'
#1325
b1000 #
b1000 -
b110111 !
b110111 .
1&
#1330
0&
0'
#1335
1&
#1340
0&
1'
#1345
b111 #
b111 -
b111000 !
b111000 .
1&
#1350
0&
0'
#1355
1&
#1360
0&
1'
#1365
b110 #
b110 -
b111001 !
b111001 .
1&
#1370
0&
0'
#1375
1&
#1380
0&
1'
#1385
b101 #
b101 -
b111010 !
b111010 .
1&
#1390
0&
0'
#1395
1&
#1400
0&
1'
#1405
b100 #
b100 -
b111011 !
b111011 .
1&
#1410
0&
0'
#1415
1&
#1420
0&
1'
#1425
b11 #
b11 -
b111100 !
b111100 .
1&
#1430
0&
0'
#1435
1&
#1440
0&
1'
#1445
b10 #
b10 -
b111101 !
b111101 .
1&
#1450
0&
0'
#1455
1&
#1460
0&
1'
#1465
b1 #
b1 -
b111110 !
b111110 .
1&
#1470
0&
0'
#1475
1&
#1480
0&
1'
#1485
1"
b0 #
b0 -
b111111 !
b111111 .
1&
#1490
0&
0'
#1495
1&
#1500
0&
1'
#1505
1&
#1510
0&
0'
#1515
1&
#1520
0&
1(
#1525
0"
b1 #
b1 -
b111110 !
b111110 .
1&
#1530
0&
0(
#1535
1&
#1540
1"
b0 #
b0 -
0&
b1010 )
b1010 +
b1010 /
#1545
1&
#1550
0&
#1555
1&
#1560
0"
b1 #
b1 -
0&
b111111 )
b111111 +
b111111 /
#1565
1&
#1570
0&
#1575
1&
#1580
b111111 #
b111111 -
b0 !
b0 .
0&
1*
#1585
1&
#1590
0&
#1595
1&
#1600
0&
0*
#1605
1&
#1610
0&
1(
#1615
1&
#1620
0&
0(
