Barrier_control/Barrier_control.v
module Barrier_control #(
    parameter BARRIER_DELAY = 10  // Delay for barrier operation
)(
    // Clock and reset
    input wire clk,              // System clock
    input wire reset,            // Synchronous reset, active high
    
    // Control inputs
    input wire open_entry,       // Signal to open entry barrier
    input wire open_exit,        // Signal to open exit barrier
    input wire close_entry,      // Signal to close entry barrier
    input wire close_exit,       // Signal to close exit barrier
    input wire emergency,        // Emergency signal
    input wire vehicle_direction, // Direction of vehicle (0: entry, 1: exit)
    
    // Barrier outputs
    output reg entry_barrier,    // Entry barrier control: 0: closed, 1: open
    output reg exit_barrier,     // Exit barrier control: 0: closed, 1: open
    output wire [1:0] barrier_status // Current barrier status
);

    // Barrier status
    localparam BARRIERS_CLOSED = 2'b00;
    localparam ENTRY_OPEN = 2'b01;
    localparam EXIT_OPEN = 2'b10;
    localparam BOTH_OPEN = 2'b11;
    
    // Barrier delay counters
    reg [9:0] entry_delay_counter;
    reg [9:0] exit_delay_counter;
    
    // Barrier operation in progress flags
    reg entry_opening;
    reg exit_opening;
    reg entry_closing;
    reg exit_closing;
    
    // Barrier status output
    assign barrier_status = {exit_barrier, entry_barrier};
    
    // Barrier control logic
    always @(posedge clk) begin
        if (reset) begin
            entry_barrier <= 1'b0;  // Closed
            exit_barrier <= 1'b0;   // Closed
            entry_delay_counter <= 10'd0;
            exit_delay_counter <= 10'd0;
            entry_opening <= 1'b0;
            exit_opening <= 1'b0;
            entry_closing <= 1'b0;
            exit_closing <= 1'b0;
        end else begin
            // Emergency handling - open both barriers immediately
            if (emergency) begin
                entry_barrier <= 1'b1;  // Open
                exit_barrier <= 1'b1;   // Open
                entry_delay_counter <= 10'd0;
                exit_delay_counter <= 10'd0;
                entry_opening <= 1'b0;
                exit_opening <= 1'b0;
                entry_closing <= 1'b0;
                exit_closing <= 1'b0;
            end else begin
                // Entry barrier control
                if (open_entry && !entry_closing && !entry_barrier) begin
                    // Start opening entry barrier
                    entry_opening <= 1'b1;
                    entry_delay_counter <= 10'd0;
                end else if (close_entry && !entry_opening) begin
                    // Start closing entry barrier
                    entry_closing <= 1'b1;
                    entry_delay_counter <= 10'd0;
                end
                
                // Exit barrier control
                if (open_exit && !exit_closing && !exit_barrier) begin
                    // Start opening exit barrier
                    exit_opening <= 1'b1;
                    exit_delay_counter <= 10'd0;
                end else if (close_exit && !exit_opening) begin
                    // Start closing exit barrier
                    exit_closing <= 1'b1;
                    exit_delay_counter <= 10'd0;
                end
                
                // Entry barrier delay handling
                if (entry_opening) begin
                    if (entry_delay_counter >= BARRIER_DELAY) begin
                        entry_barrier <= 1'b1;  // Open
                        entry_opening <= 1'b0;
                    end else begin
                        entry_delay_counter <= entry_delay_counter + 10'd1;
                    end
                end else if (entry_closing) begin
                    if (entry_delay_counter >= BARRIER_DELAY / 2) begin  // Close faster
                        entry_barrier <= 1'b0;  // Closed
                        entry_closing <= 1'b0;
                    end else begin
                        entry_delay_counter <= entry_delay_counter + 10'd1;
                    end
                end
                
                // Exit barrier delay handling
                if (exit_opening) begin
                    if (exit_delay_counter >= BARRIER_DELAY) begin
                        exit_barrier <= 1'b1;  // Open
                        exit_opening <= 1'b0;
                    end else begin
                        exit_delay_counter <= exit_delay_counter + 10'd1;
                    end
                end else if (exit_closing) begin
                    if (exit_delay_counter >= BARRIER_DELAY / 2) begin  // Close faster
                        exit_barrier <= 1'b0;  // Closed
                        exit_closing <= 1'b0;
                    end else begin
                        exit_delay_counter <= exit_delay_counter + 10'd1;
                    end
                end
                
                // Priority handling - if close command is received during opening
                if (close_entry && entry_opening && entry_delay_counter < BARRIER_DELAY/2) begin
                    entry_opening <= 1'b0;
                    entry_closing <= 1'b1;
                    entry_delay_counter <= 10'd0;
                end
                
                if (close_exit && exit_opening && exit_delay_counter < BARRIER_DELAY/2) begin
                    exit_opening <= 1'b0;
                    exit_closing <= 1'b1;
                    exit_delay_counter <= 10'd0;
                end
            end
        end
    end

endmodule

Barrier_control/Barrier_control_tb.v
module Barrier_control_tb;
    // Parameters
    parameter CLK_PERIOD = 10;       // Clock period in ns
    parameter BARRIER_DELAY = 10;    // Barrier delay for testing
    parameter MAX_WAIT = 50;         // Maximum wait cycles for barrier operations
    
    // Testbench signals
    reg clk;
    reg reset;
    reg open_entry;
    reg open_exit;
    reg close_entry;
    reg close_exit;
    reg emergency;
    reg vehicle_direction;
    
    wire entry_barrier;
    wire exit_barrier;
    wire [1:0] barrier_status;
    
    // Internal signals for monitoring
    wire entry_opening;
    wire exit_opening;
    wire entry_closing;
    wire exit_closing;
    
    // Instantiate the Unit Under Test (UUT)
    Barrier_control #(
        .BARRIER_DELAY(BARRIER_DELAY)
    ) uut (
        .clk(clk),
        .reset(reset),
        .open_entry(open_entry),
        .open_exit(open_exit),
        .close_entry(close_entry),
        .close_exit(close_exit),
        .emergency(emergency),
        .vehicle_direction(vehicle_direction),
        .entry_barrier(entry_barrier),
        .exit_barrier(exit_barrier),
        .barrier_status(barrier_status)
    );
    
    // Connect internal signals for monitoring (if needed)
    assign entry_opening = uut.entry_opening;
    assign exit_opening = uut.exit_opening;
    assign entry_closing = uut.entry_closing;
    assign exit_closing = uut.exit_closing;
    
    // VCD file generation for GTKWave
    initial begin
        $dumpfile("barrier_control_waveform.vcd");
        $dumpvars(0, Barrier_control_tb);
    end
    
    // Clock generation
    initial begin
        clk = 0;
        forever #(CLK_PERIOD/2) clk = ~clk;
    end
    
    // Function to return barrier status as a string
    function [64*8-1:0] decode_barrier_status;
        input [1:0] status;
        begin
            case (status)
                2'b00: decode_barrier_status = "BARRIERS_CLOSED";
                2'b01: decode_barrier_status = "ENTRY_OPEN";
                2'b10: decode_barrier_status = "EXIT_OPEN";
                2'b11: decode_barrier_status = "BOTH_OPEN";
                default: decode_barrier_status = "UNKNOWN";
            endcase
        end
    endfunction
    
    // Display status changes
    always @(barrier_status or entry_barrier or exit_barrier) begin
        $display("Time=%0t: entry_barrier=%0b, exit_barrier=%0b, barrier_status=%0b (%s)", 
                 $time, entry_barrier, exit_barrier, barrier_status, decode_barrier_status(barrier_status));
    end
    
    // Display internal state changes
    always @(entry_opening or exit_opening or entry_closing or exit_closing) begin
        $display("Time=%0t: Internal state - entry_opening=%0b, exit_opening=%0b, entry_closing=%0b, exit_closing=%0b", 
                 $time, entry_opening, exit_opening, entry_closing, exit_closing);
    end
    
    // Task to wait for barrier operation to complete with timeout
    task wait_for_barrier_operation;
        input is_entry;
        input is_opening;
        integer wait_count;
        begin
            wait_count = 0;
            
            if (is_entry && is_opening) begin
                // Wait for entry barrier to open fully
                while (wait_count < MAX_WAIT) begin
                    if (!entry_opening && entry_barrier) begin
                        $display("Time=%0t: Entry barrier fully opened", $time);
                        wait_count = MAX_WAIT; // Exit loop
                    end else begin
                        #(CLK_PERIOD);
                        wait_count = wait_count + 1;
                    end
                end
                if (wait_count == MAX_WAIT && (entry_opening || !entry_barrier))
                    $display("Time=%0t: WARNING - Timeout waiting for entry barrier to open", $time);
            end else if (is_entry && !is_opening) begin
                // Wait for entry barrier to close fully
                while (wait_count < MAX_WAIT) begin
                    if (!entry_closing && !entry_barrier) begin
                        $display("Time=%0t: Entry barrier fully closed", $time);
                        wait_count = MAX_WAIT; // Exit loop
                    end else begin
                        #(CLK_PERIOD);
                        wait_count = wait_count + 1;
                    end
                end
                if (wait_count == MAX_WAIT && (entry_closing || entry_barrier))
                    $display("Time=%0t: WARNING - Timeout waiting for entry barrier to close", $time);
            end else if (!is_entry && is_opening) begin
                // Wait for exit barrier to open fully
                while (wait_count < MAX_WAIT) begin
                    if (!exit_opening && exit_barrier) begin
                        $display("Time=%0t: Exit barrier fully opened", $time);
                        wait_count = MAX_WAIT; // Exit loop
                    end else begin
                        #(CLK_PERIOD);
                        wait_count = wait_count + 1;
                    end
                end
                if (wait_count == MAX_WAIT && (exit_opening || !exit_barrier))
                    $display("Time=%0t: WARNING - Timeout waiting for exit barrier to open", $time);
            end else if (!is_entry && !is_opening) begin
                // Wait for exit barrier to close fully
                while (wait_count < MAX_WAIT) begin
                    if (!exit_closing && !exit_barrier) begin
                        $display("Time=%0t: Exit barrier fully closed", $time);
                        wait_count = MAX_WAIT; // Exit loop
                    end else begin
                        #(CLK_PERIOD);
                        wait_count = wait_count + 1;
                    end
                end
                if (wait_count == MAX_WAIT && (exit_closing || exit_barrier))
                    $display("Time=%0t: WARNING - Timeout waiting for exit barrier to close", $time);
            end
        end
    endtask
    
    // Test stimulus
    initial begin
        // Initialize inputs
        reset = 1;
        open_entry = 0;
        open_exit = 0;
        close_entry = 0;
        close_exit = 0;
        emergency = 0;
        vehicle_direction = 0;
        
        // Apply reset
        #(CLK_PERIOD*2);
        reset = 0;
        #(CLK_PERIOD);
        
        // Display initial state
        $display("\nTime=%0t: Initial state - entry_barrier=%0b, exit_barrier=%0b, barrier_status=%0b", 
                 $time, entry_barrier, exit_barrier, barrier_status);
        
        // Test Case 1: Open entry barrier
        $display("\nTest Case 1: Open entry barrier");
        open_entry = 1;
        #(CLK_PERIOD);
        open_entry = 0;
        wait_for_barrier_operation(1, 1);
        $display("Time=%0t: After open entry - entry_barrier=%0b, exit_barrier=%0b, barrier_status=%0b", 
                 $time, entry_barrier, exit_barrier, barrier_status);
        
        // Test Case 2: Close entry barrier
        $display("\nTest Case 2: Close entry barrier");
        close_entry = 1;
        #(CLK_PERIOD);
        close_entry = 0;
        wait_for_barrier_operation(1, 0);
        $display("Time=%0t: After close entry - entry_barrier=%0b, exit_barrier=%0b, barrier_status=%0b", 
                 $time, entry_barrier, exit_barrier, barrier_status);
        
        // Test Case 3: Open exit barrier
        $display("\nTest Case 3: Open exit barrier");
        open_exit = 1;
        #(CLK_PERIOD);
        open_exit = 0;
        wait_for_barrier_operation(0, 1);
        $display("Time=%0t: After open exit - entry_barrier=%0b, exit_barrier=%0b, barrier_status=%0b", 
                 $time, entry_barrier, exit_barrier, barrier_status);
        
        // Test Case 4: Close exit barrier
        $display("\nTest Case 4: Close exit barrier");
        close_exit = 1;
        #(CLK_PERIOD);
        close_exit = 0;
        wait_for_barrier_operation(0, 0);
        $display("Time=%0t: After close exit - entry_barrier=%0b, exit_barrier=%0b, barrier_status=%0b", 
                 $time, entry_barrier, exit_barrier, barrier_status);
        
        // Test Case 5: Emergency mode
        $display("\nTest Case 5: Emergency mode");
        emergency = 1;
        #(CLK_PERIOD * 5);
        $display("Time=%0t: During emergency - entry_barrier=%0b, exit_barrier=%0b, barrier_status=%0b", 
                 $time, entry_barrier, exit_barrier, barrier_status);
        
        // End emergency and close barriers
        emergency = 0;
        #(CLK_PERIOD * 5);
        close_entry = 1;
        close_exit = 1;
        #(CLK_PERIOD);
        close_entry = 0;
        close_exit = 0;
        wait_for_barrier_operation(1, 0);
        wait_for_barrier_operation(0, 0);
        $display("Time=%0t: After emergency - entry_barrier=%0b, exit_barrier=%0b, barrier_status=%0b", 
                 $time, entry_barrier, exit_barrier, barrier_status);
        
        // Test Case 6: Simultaneous open commands
        $display("\nTest Case 6: Simultaneous open commands");
        open_entry = 1;
        open_exit = 1;
        #(CLK_PERIOD);
        open_entry = 0;
        open_exit = 0;
        wait_for_barrier_operation(1, 1);
        wait_for_barrier_operation(0, 1);
        $display("Time=%0t: After simultaneous open - entry_barrier=%0b, exit_barrier=%0b, barrier_status=%0b", 
                 $time, entry_barrier, exit_barrier, barrier_status);
        
        // Test Case 7: Simultaneous close commands
        $display("\nTest Case 7: Simultaneous close commands");
        close_entry = 1;
        close_exit = 1;
        #(CLK_PERIOD);
        close_entry = 0;
        close_exit = 0;
        wait_for_barrier_operation(1, 0);
        wait_for_barrier_operation(0, 0);
        $display("Time=%0t: After simultaneous close - entry_barrier=%0b, exit_barrier=%0b, barrier_status=%0b", 
                 $time, entry_barrier, exit_barrier, barrier_status);
        
        // Test Case 8: Priority of close over open
        $display("\nTest Case 8: Priority of close over open");
        // First open the barriers
        open_entry = 1;
        #(CLK_PERIOD);
        open_entry = 0;
        #(CLK_PERIOD * (BARRIER_DELAY/2)); // Wait half the delay
        
        // Now try to close while still opening
        close_entry = 1;
        #(CLK_PERIOD);
        close_entry = 0;
        wait_for_barrier_operation(1, 0);
        $display("Time=%0t: After priority test - entry_barrier=%0b, exit_barrier=%0b, barrier_status=%0b", 
                 $time, entry_barrier, exit_barrier, barrier_status);
        
        // Test Case 9: Reset during operation
        $display("\nTest Case 9: Reset during operation");
        open_entry = 1;
        open_exit = 1;
        #(CLK_PERIOD);
        open_entry = 0;
        open_exit = 0;
        #(CLK_PERIOD * (BARRIER_DELAY/2));
        reset = 1;
        #(CLK_PERIOD*2);
        reset = 0;
        #(CLK_PERIOD*5);
        $display("Time=%0t: After reset - entry_barrier=%0b, exit_barrier=%0b, barrier_status=%0b", 
                 $time, entry_barrier, exit_barrier, barrier_status);
        
        // Test Case 10: Faster closing time
        $display("\nTest Case 10: Faster closing time");
        // Open entry barrier
        open_entry = 1;
        #(CLK_PERIOD);
        open_entry = 0;
        wait_for_barrier_operation(1, 1);
        
        // Measure time to close
        $display("Time=%0t: Starting barrier close timing test", $time);
        close_entry = 1;
        #(CLK_PERIOD);
        close_entry = 0;
        wait_for_barrier_operation(1, 0);
        $display("Time=%0t: Barrier close timing test completed", $time);
        
        // End simulation
        #(CLK_PERIOD*10);
        $display("\nSimulation completed successfully");
        $finish;
    end
endmodule

Barrier_control/barrier_control_waveform.vcd
$date
	Mon Jun 16 12:21:14 2025
$end
$version
	Icarus Verilog
$end
$timescale
	1s
$end
$scope module Barrier_control_tb $end
$var wire 1 ! entry_closing $end
$var wire 1 " entry_opening $end
$var wire 1 # exit_closing $end
$var wire 1 $ exit_opening $end
$var wire 1 % exit_barrier $end
$var wire 1 & entry_barrier $end
$var wire 2 ' barrier_status [1:0] $end
$var parameter 32 ( BARRIER_DELAY $end
$var parameter 32 ) CLK_PERIOD $end
$var parameter 32 * MAX_WAIT $end
$var reg 1 + clk $end
$var reg 1 , close_entry $end
$var reg 1 - close_exit $end
$var reg 1 . emergency $end
$var reg 1 / open_entry $end
$var reg 1 0 open_exit $end
$var reg 1 1 reset $end
$var reg 1 2 vehicle_direction $end
$scope function decode_barrier_status $end
$var reg 2 3 status [1:0] $end
$upscope $end
$scope module uut $end
$var wire 1 + clk $end
$var wire 1 , close_entry $end
$var wire 1 - close_exit $end
$var wire 1 . emergency $end
$var wire 1 / open_entry $end
$var wire 1 0 open_exit $end
$var wire 1 1 reset $end
$var wire 1 2 vehicle_direction $end
$var wire 2 4 barrier_status [1:0] $end
$var parameter 2 5 BARRIERS_CLOSED $end
$var parameter 32 6 BARRIER_DELAY $end
$var parameter 2 7 BOTH_OPEN $end
$var parameter 2 8 ENTRY_OPEN $end
$var parameter 2 9 EXIT_OPEN $end
$var reg 1 & entry_barrier $end
$var reg 1 : entry_closing $end
$var reg 10 ; entry_delay_counter [9:0] $end
$var reg 1 < entry_opening $end
$var reg 1 % exit_barrier $end
$var reg 1 = exit_closing $end
$var reg 10 > exit_delay_counter [9:0] $end
$var reg 1 ? exit_opening $end
$upscope $end
$scope task wait_for_barrier_operation $end
$var reg 1 @ is_entry $end
$var reg 1 A is_opening $end
$var integer 32 B wait_count [31:0] $end
$upscope $end
$upscope $end
$enddefinitions $end
$comment Show the parameter values. $end
$dumpall
b10 9
b1 8
b11 7
b1010 6
b0 5
b110010 *
b1010 )
b1010 (
$end
#0
$dumpvars
bx B
xA
x@
x?
bx >
x=
x<
bx ;
x:
bx 4
bx 3
02
11
00
0/
0.
0-
0,
0+
bx '
x&
x%
x$
x#
x"
x!
$end
#5
b0 3
b0 '
b0 4
0#
0=
0!
0:
0$
0?
0"
0<
b0 >
b0 ;
0%
0&
1+
#10
0+
#15
1+
#20
0+
01
#25
1+
#30
0+
1/
#35
1"
1<
1+
#40
0+
b0 B
1A
1@
0/
#45
b1 ;
1+
#50
0+
b1 B
#55
b10 ;
1+
#60
0+
b10 B
#65
b11 ;
1+
#70
0+
b11 B
#75
b100 ;
1+
#80
0+
b100 B
#85
b101 ;
1+
#90
0+
b101 B
#95
b110 ;
1+
#100
0+
b110 B
#105
b111 ;
1+
#110
0+
b111 B
#115
b1000 ;
1+
#120
0+
b1000 B
#125
b1001 ;
1+
#130
0+
b1001 B
#135
b1010 ;
1+
#140
0+
b1010 B
#145
b1 3
b1 '
b1 4
0"
0<
1&
1+
#150
0+
1,
b110010 B
#155
b0 ;
1!
1:
1+
#160
0+
b0 B
0A
0,
#165
b1 ;
1+
#170
0+
b1 B
#175
b10 ;
1+
#180
0+
b10 B
#185
b11 ;
1+
#190
0+
b11 B
#195
b100 ;
1+
#200
0+
b100 B
#205
b101 ;
1+
#210
0+
b101 B
#215
b0 3
b0 '
b0 4
0!
0:
0&
1+
#220
0+
10
b110010 B
#225
1$
1?
1+
#230
0+
b0 B
1A
0@
00
#235
b1 >
1+
#240
0+
b1 B
#245
b10 >
1+
#250
0+
b10 B
#255
b11 >
1+
#260
0+
b11 B
#265
b100 >
1+
#270
0+
b100 B
#275
b101 >
1+
#280
0+
b101 B
#285
b110 >
1+
#290
0+
b110 B
#295
b111 >
1+
#300
0+
b111 B
#305
b1000 >
1+
#310
0+
b1000 B
#315
b1001 >
1+
#320
0+
b1001 B
#325
b1010 >
1+
#330
0+
b1010 B
#335
b10 3
b10 '
b10 4
0$
0?
1%
1+
#340
0+
1-
b110010 B
#345
b0 >
1#
1=
1+
#350
0+
b0 B
0A
0-
#355
b1 >
1+
#360
0+
b1 B
#365
b10 >
1+
#370
0+
b10 B
#375
b11 >
1+
#380
0+
b11 B
#385
b100 >
1+
#390
0+
b100 B
#395
b101 >
1+
#400
0+
b101 B
#405
b0 3
b0 '
b0 4
0#
0=
0%
1+
#410
0+
1.
b110010 B
#415
b11 3
b11 '
b11 4
b0 >
b0 ;
1%
1&
1+
#420
0+
#425
1+
#430
0+
#435
1+
#440
0+
#445
1+
#450
0+
#455
1+
#460
0+
0.
#465
1+
#470
0+
#475
1+
#480
0+
#485
1+
#490
0+
#495
1+
#500
0+
#505
1+
#510
0+
1-
1,
#515
1#
1=
1!
1:
1+
#520
0+
b0 B
1@
0-
0,
#525
b1 >
b1 ;
1+
#530
0+
b1 B
#535
b10 >
b10 ;
1+
#540
0+
b10 B
#545
b11 >
b11 ;
1+
#550
0+
b11 B
#555
b100 >
b100 ;
1+
#560
0+
b100 B
#565
b101 >
b101 ;
1+
#570
0+
b101 B
#575
b0 3
b0 '
b0 4
0#
0=
0%
0!
0:
0&
1+
#580
0+
10
1/
0@
b110010 B
#585
b0 >
1$
1?
b0 ;
1"
1<
1+
#590
0+
b0 B
1A
1@
00
0/
#595
b1 >
b1 ;
1+
#600
0+
b1 B
#605
b10 >
b10 ;
1+
#610
0+
b10 B
#615
b11 >
b11 ;
1+
#620
0+
b11 B
#625
b100 >
b100 ;
1+
#630
0+
b100 B
#635
b101 >
b101 ;
1+
#640
0+
b101 B
#645
b110 >
b110 ;
1+
#650
0+
b110 B
#655
b111 >
b111 ;
1+
#660
0+
b111 B
#665
b1000 >
b1000 ;
1+
#670
0+
b1000 B
#675
b1001 >
b1001 ;
1+
#680
0+
b1001 B
#685
b1010 >
b1010 ;
1+
#690
0+
b1010 B
#695
b11 3
b11 '
b11 4
0$
0?
1%
0"
0<
1&
1+
#700
0+
1-
1,
0@
b110010 B
#705
b0 >
1#
1=
b0 ;
1!
1:
1+
#710
0+
b0 B
0A
1@
0-
0,
#715
b1 >
b1 ;
1+
#720
0+
b1 B
#725
b10 >
b10 ;
1+
#730
0+
b10 B
#735
b11 >
b11 ;
1+
#740
0+
b11 B
#745
b100 >
b100 ;
1+
#750
0+
b100 B
#755
b101 >
b101 ;
1+
#760
0+
b101 B
#765
b0 3
b0 '
b0 4
0#
0=
0%
0!
0:
0&
1+
#770
0+
1/
0@
b110010 B
#775
b0 ;
1"
1<
1+
#780
0+
0/
#785
b1 ;
1+
#790
0+
#795
b10 ;
1+
#800
0+
#805
b11 ;
1+
#810
0+
#815
b100 ;
1+
#820
0+
#825
b101 ;
1+
#830
0+
1,
#835
b110 ;
1+
#840
0+
10
1/
b110010 B
1@
0,
#845
b0 >
1$
1?
b111 ;
1+
#850
0+
00
0/
#855
b1 >
b1000 ;
1+
#860
0+
#865
b10 >
b1001 ;
1+
#870
0+
#875
b11 >
b1010 ;
1+
#880
0+
#885
b1 3
b1 '
b1 4
b100 >
0"
0<
1&
1+
#890
0+
#895
b101 >
1+
#900
0+
11
#905
b0 3
b0 '
b0 4
0$
0?
b0 >
b0 ;
0&
1+
#910
0+
#915
1+
#920
0+
01
#925
1+
#930
0+
#935
1+
#940
0+
#945
1+
#950
0+
#955
1+
#960
0+
#965
1+
#970
0+
1/
#975
1"
1<
1+
#980
0+
b0 B
1A
0/
#985
b1 ;
1+
#990
0+
b1 B
#995
b10 ;
1+
#1000
0+
b10 B
#1005
b11 ;
1+
#1010
0+
b11 B
#1015
b100 ;
1+
#1020
0+
b100 B
#1025
b101 ;
1+
#1030
0+
b101 B
#1035
b110 ;
1+
#1040
0+
b110 B
#1045
b111 ;
1+
#1050
0+
b111 B
#1055
b1000 ;
1+
#1060
0+
b1000 B
#1065
b1001 ;
1+
#1070
0+
b1001 B
#1075
b1010 ;
1+
#1080
0+
b1010 B
#1085
b1 3
b1 '
b1 4
0"
0<
1&
1+
#1090
0+
1,
b110010 B
#1095
b0 ;
1!
1:
1+
#1100
0+
b0 B
0A
0,
#1105
b1 ;
1+
#1110
0+
b1 B
#1115
b10 ;
1+
#1120
0+
b10 B
#1125
b11 ;
1+
#1130
0+
b11 B
#1135
b100 ;
1+
#1140
0+
b100 B
#1145
b101 ;
1+
#1150
0+
b101 B
#1155
b0 3
b0 '
b0 4
0!
0:
0&
1+
#1160
0+
b110010 B
